{
  "sourceId": "guimet",
  "sourceName": "Musée Guimet",
  "schemaVersion": 1,
  "lastFetched": "2026-05-10T03:21:45.797Z",
  "items": [
    {
      "img": "https://commons.wikimedia.org/wiki/Special:FilePath/Brahma-MG%2018100-IMG%200536-black.jpg",
      "thumb": "https://commons.wikimedia.org/wiki/Special:FilePath/Brahma-MG%2018100-IMG%200536-black.jpg?width=400",
      "title": "Brahma-MG_18100",
      "source": "guimet",
      "tags": [
        "portrait"
      ]
    },
    {
      "img": "https://commons.wikimedia.org/wiki/Special:FilePath/Visnu-MG%2018102-IMG%200532-black.jpg",
      "thumb": "https://commons.wikimedia.org/wiki/Special:FilePath/Visnu-MG%2018102-IMG%200532-black.jpg?width=400",
      "title": "Visnu MG_18102",
      "source": "guimet",
      "tags": [
        "portrait"
      ]
    },
    {
      "img": "https://commons.wikimedia.org/wiki/Special:FilePath/Siva-MG%2018101-IMG%200534-black.jpg",
      "thumb": "https://commons.wikimedia.org/wiki/Special:FilePath/Siva-MG%2018101-IMG%200534-black.jpg?width=400",
      "title": "Siva-MG 18101",
      "source": "guimet",
      "tags": [
        "portrait"
      ]
    },
    {
      "img": "https://commons.wikimedia.org/wiki/Special:FilePath/Helmet-MA%2012684-IMG%208850.jpg",
      "thumb": "https://commons.wikimedia.org/wiki/Special:FilePath/Helmet-MA%2012684-IMG%208850.jpg?width=400",
      "title": "Helmet",
      "source": "guimet",
      "tags": [
        "portrait"
      ]
    },
    {
      "img": "https://commons.wikimedia.org/wiki/Special:FilePath/Dancer-MA%206122%20a%208714-gradient.jpg",
      "thumb": "https://commons.wikimedia.org/wiki/Special:FilePath/Dancer-MA%206122%20a%208714-gradient.jpg?width=400",
      "title": "Dancer",
      "source": "guimet",
      "tags": [
        "portrait"
      ]
    },
    {
      "img": "https://commons.wikimedia.org/wiki/Special:FilePath/Hokusai%201760-1849%20Ocean%20waves.jpg",
      "thumb": "https://commons.wikimedia.org/wiki/Special:FilePath/Hokusai%201760-1849%20Ocean%20waves.jpg?width=400",
      "title": "Fishing boats at Chōshi in Fusa Province (Shimosa)",
      "source": "guimet",
      "tags": [
        "portrait"
      ]
    },
    {
      "img": "https://commons.wikimedia.org/wiki/Special:FilePath/Hokusai%20au%20mus%C3%A9e%20Guimet%20%288207201922%29.jpg",
      "thumb": "https://commons.wikimedia.org/wiki/Special:FilePath/Hokusai%20au%20mus%C3%A9e%20Guimet%20%288207201922%29.jpg?width=400",
      "title": "Fishing boats at Chōshi in Fusa Province (Shimosa)",
      "source": "guimet",
      "tags": [
        "portrait"
      ]
    },
    {
      "img": "https://commons.wikimedia.org/wiki/Special:FilePath/Hokusai%2C%20mille%20immagini%20del%20mare%2C%20choshi%20nella%20provincia%20di%20chiba%2C%201832-34.JPG",
      "thumb": "https://commons.wikimedia.org/wiki/Special:FilePath/Hokusai%2C%20mille%20immagini%20del%20mare%2C%20choshi%20nella%20provincia%20di%20chiba%2C%201832-34.JPG?width=400",
      "title": "Fishing boats at Chōshi in Fusa Province (Shimosa)",
      "source": "guimet",
      "tags": [
        "portrait"
      ]
    },
    {
      "img": "https://commons.wikimedia.org/wiki/Special:FilePath/Portrait%20of%20Toki%20Yorisada-EO%201-IMG%208981-gradient.jpg",
      "thumb": "https://commons.wikimedia.org/wiki/Special:FilePath/Portrait%20of%20Toki%20Yorisada-EO%201-IMG%208981-gradient.jpg?width=400",
      "title": "portrait of Toki Yorisada-EO 1",
      "source": "guimet",
      "tags": [
        "portrait"
      ]
    },
    {
      "img": "https://commons.wikimedia.org/wiki/Special:FilePath/Candlestick-MA%203746-IMG%209200-gradient.jpg",
      "thumb": "https://commons.wikimedia.org/wiki/Special:FilePath/Candlestick-MA%203746-IMG%209200-gradient.jpg?width=400",
      "title": "Candlestick MA 3746",
      "source": "guimet",
      "tags": [
        "portrait"
      ]
    },
    {
      "img": "https://commons.wikimedia.org/wiki/Special:FilePath/Se%20player-MA%202949-IMG%208724-gradient.jpg",
      "thumb": "https://commons.wikimedia.org/wiki/Special:FilePath/Se%20player-MA%202949-IMG%208724-gradient.jpg?width=400",
      "title": "Statue of a se player",
      "source": "guimet",
      "tags": [
        "portrait"
      ]
    },
    {
      "img": "https://commons.wikimedia.org/wiki/Special:FilePath/Sitting%20Buddha%20meditating-EO%201100-IMG%208609-gradient.jpg",
      "thumb": "https://commons.wikimedia.org/wiki/Special:FilePath/Sitting%20Buddha%20meditating-EO%201100-IMG%208609-gradient.jpg?width=400",
      "title": "Buddha EO 1100",
      "source": "guimet",
      "tags": [
        "portrait"
      ]
    },
    {
      "img": "https://commons.wikimedia.org/wiki/Special:FilePath/Sitted%20lion-AA%20190-IMG%208632-gradient.jpg",
      "thumb": "https://commons.wikimedia.org/wiki/Special:FilePath/Sitted%20lion-AA%20190-IMG%208632-gradient.jpg?width=400",
      "title": "Sitted lion AA 190",
      "source": "guimet",
      "tags": [
        "portrait"
      ]
    },
    {
      "img": "https://commons.wikimedia.org/wiki/Special:FilePath/Aureola%20fragment-the%20seven%20buddha%20of%20the%20past-MG%2023767-IMG%208601-gradient.jpg",
      "thumb": "https://commons.wikimedia.org/wiki/Special:FilePath/Aureola%20fragment-the%20seven%20buddha%20of%20the%20past-MG%2023767-IMG%208601-gradient.jpg?width=400",
      "title": "Aureola fragment: the seven buddha of the past",
      "source": "guimet",
      "tags": [
        "portrait"
      ]
    },
    {
      "img": "https://commons.wikimedia.org/wiki/Special:FilePath/Camel-MA%206721-IMG%208692-gradient.jpg",
      "thumb": "https://commons.wikimedia.org/wiki/Special:FilePath/Camel-MA%206721-IMG%208692-gradient.jpg?width=400",
      "title": "statue of a camel and camel driver",
      "source": "guimet",
      "tags": [
        "portrait"
      ]
    },
    {
      "img": "https://commons.wikimedia.org/wiki/Special:FilePath/Head%20of%20Maitreya-AO%202911-IMG%208467-gradient.jpg",
      "thumb": "https://commons.wikimedia.org/wiki/Special:FilePath/Head%20of%20Maitreya-AO%202911-IMG%208467-gradient.jpg?width=400",
      "title": "Head of Maitreya-AO 2911",
      "source": "guimet",
      "tags": [
        "portrait"
      ]
    },
    {
      "img": "https://commons.wikimedia.org/wiki/Special:FilePath/Immortals-G%205595-G%205596-IMG%209083-gradient.jpg",
      "thumb": "https://commons.wikimedia.org/wiki/Special:FilePath/Immortals-G%205595-G%205596-IMG%209083-gradient.jpg?width=400",
      "title": "Immortals-G_5595-G_5596",
      "source": "guimet",
      "tags": [
        "portrait"
      ]
    },
    {
      "img": "https://commons.wikimedia.org/wiki/Special:FilePath/Appeasing%20Buddha%20with%20jewel-MA%20656-IMG%208665-gradient.jpg",
      "thumb": "https://commons.wikimedia.org/wiki/Special:FilePath/Appeasing%20Buddha%20with%20jewel-MA%20656-IMG%208665-gradient.jpg?width=400",
      "title": "Appeasing Buddha with jewel",
      "source": "guimet",
      "tags": [
        "portrait"
      ]
    },
    {
      "img": "https://commons.wikimedia.org/wiki/Special:FilePath/Katana%20blade%201505%20Osofune%20school-MA%206943-IMG%209000-gradient.jpg",
      "thumb": "https://commons.wikimedia.org/wiki/Special:FilePath/Katana%20blade%201505%20Osofune%20school-MA%206943-IMG%209000-gradient.jpg?width=400",
      "title": "katana blade",
      "source": "guimet",
      "tags": [
        "portrait"
      ]
    },
    {
      "img": "https://commons.wikimedia.org/wiki/Special:FilePath/Ichtyomorph%20bottles-IMG%208544-gradient.jpg",
      "thumb": "https://commons.wikimedia.org/wiki/Special:FilePath/Ichtyomorph%20bottles-IMG%208544-gradient.jpg?width=400",
      "title": "ichthyomorphic bottle",
      "source": "guimet",
      "tags": [
        "portrait"
      ]
    },
    {
      "img": "https://commons.wikimedia.org/wiki/Special:FilePath/Qin%20player-MG%2018914-IMG%208639-gradient.jpg",
      "thumb": "https://commons.wikimedia.org/wiki/Special:FilePath/Qin%20player-MG%2018914-IMG%208639-gradient.jpg?width=400",
      "title": "Qin player",
      "source": "guimet",
      "tags": [
        "portrait"
      ]
    },
    {
      "img": "https://commons.wikimedia.org/wiki/Special:FilePath/Nasta%27liq%20calligraphy%20style%20-%20Jafar%20Tabrizi%2002.png",
      "thumb": "https://commons.wikimedia.org/wiki/Special:FilePath/Nasta%27liq%20calligraphy%20style%20-%20Jafar%20Tabrizi%2002.png?width=400",
      "title": "Golshan Album",
      "source": "guimet",
      "tags": [
        "portrait"
      ]
    },
    {
      "img": "https://commons.wikimedia.org/wiki/Special:FilePath/Bodhisattva-MG%2018959-IMG%208587-gradient.jpg",
      "thumb": "https://commons.wikimedia.org/wiki/Special:FilePath/Bodhisattva-MG%2018959-IMG%208587-gradient.jpg?width=400",
      "title": "Bodhisattva-MG 18959",
      "source": "guimet",
      "tags": [
        "portrait"
      ]
    },
    {
      "img": "https://commons.wikimedia.org/wiki/Special:FilePath/Grimacing%20mask-MG%2017738-IMG%208589-gradient.jpg",
      "thumb": "https://commons.wikimedia.org/wiki/Special:FilePath/Grimacing%20mask-MG%2017738-IMG%208589-gradient.jpg?width=400",
      "title": "grimacing mask",
      "source": "guimet",
      "tags": [
        "portrait"
      ]
    },
    {
      "img": "https://commons.wikimedia.org/wiki/Special:FilePath/Omi-MA%203259-IMG%208877-gradient.jpg",
      "thumb": "https://commons.wikimedia.org/wiki/Special:FilePath/Omi-MA%203259-IMG%208877-gradient.jpg?width=400",
      "title": "Omi-MA 3259",
      "source": "guimet",
      "tags": [
        "portrait"
      ]
    },
    {
      "img": "https://commons.wikimedia.org/wiki/Special:FilePath/Le%20rossignol%20dans%20les%20bambous%20%28mus%C3%A9e%20Guimet%29%20%2815342675419%29.jpg",
      "thumb": "https://commons.wikimedia.org/wiki/Special:FilePath/Le%20rossignol%20dans%20les%20bambous%20%28mus%C3%A9e%20Guimet%29%20%2815342675419%29.jpg?width=400",
      "title": "The nightingale in the bamboo ( Takema No. Uguisu )",
      "source": "guimet",
      "tags": [
        "landscape"
      ]
    },
    {
      "img": "https://commons.wikimedia.org/wiki/Special:FilePath/Dui%20ovoid%20vase-MA%203880-IMG%209443-gradient.jpg",
      "thumb": "https://commons.wikimedia.org/wiki/Special:FilePath/Dui%20ovoid%20vase-MA%203880-IMG%209443-gradient.jpg?width=400",
      "title": "Dui ovoid vase-MA 3880",
      "source": "guimet",
      "tags": [
        "landscape"
      ]
    },
    {
      "img": "https://commons.wikimedia.org/wiki/Special:FilePath/Quing-era%20cup-G%203494-IMG%209116-gradient.jpg",
      "thumb": "https://commons.wikimedia.org/wiki/Special:FilePath/Quing-era%20cup-G%203494-IMG%209116-gradient.jpg?width=400",
      "title": "Quing-era cup-G 3494",
      "source": "guimet",
      "tags": [
        "landscape"
      ]
    },
    {
      "img": "https://commons.wikimedia.org/wiki/Special:FilePath/Floral%20pattern%20pot-MA%204196-IMG%209167-gradient.jpg",
      "thumb": "https://commons.wikimedia.org/wiki/Special:FilePath/Floral%20pattern%20pot-MA%204196-IMG%209167-gradient.jpg?width=400",
      "title": "Floral pattern pot-MA 4196",
      "source": "guimet",
      "tags": [
        "landscape"
      ]
    },
    {
      "img": "https://commons.wikimedia.org/wiki/Special:FilePath/Bowl-MG%208534-IMG%209239-gradient.jpg",
      "thumb": "https://commons.wikimedia.org/wiki/Special:FilePath/Bowl-MG%208534-IMG%209239-gradient.jpg?width=400",
      "title": "Bowl-MG 8534",
      "source": "guimet",
      "tags": [
        "landscape"
      ]
    },
    {
      "img": "https://commons.wikimedia.org/wiki/Special:FilePath/Jar-MA%204189-IMG%209162-gradient.jpg",
      "thumb": "https://commons.wikimedia.org/wiki/Special:FilePath/Jar-MA%204189-IMG%209162-gradient.jpg?width=400",
      "title": "Jar-MA 4189",
      "source": "guimet",
      "tags": [
        "landscape"
      ]
    },
    {
      "img": "https://commons.wikimedia.org/wiki/Special:FilePath/Yi%20container-AA%2078-IMG%209414-gradient.jpg",
      "thumb": "https://commons.wikimedia.org/wiki/Special:FilePath/Yi%20container-AA%2078-IMG%209414-gradient.jpg?width=400",
      "title": "Yi container-AA 78",
      "source": "guimet",
      "tags": [
        "landscape"
      ]
    },
    {
      "img": "https://commons.wikimedia.org/wiki/Special:FilePath/Perfume%20burner-03-008563-IMG%209060-gradient.jpg",
      "thumb": "https://commons.wikimedia.org/wiki/Special:FilePath/Perfume%20burner-03-008563-IMG%209060-gradient.jpg?width=400",
      "title": "Perfume burner-03-008563",
      "source": "guimet",
      "tags": [
        "landscape"
      ]
    },
    {
      "img": "https://commons.wikimedia.org/wiki/Special:FilePath/Hokusai%20au%20mus%C3%A9e%20Guimet%20%288290871756%29.jpg",
      "thumb": "https://commons.wikimedia.org/wiki/Special:FilePath/Hokusai%20au%20mus%C3%A9e%20Guimet%20%288290871756%29.jpg?width=400",
      "title": "poem by Fujiwara no Michinobu",
      "source": "guimet",
      "tags": [
        "landscape"
      ]
    },
    {
      "img": "https://commons.wikimedia.org/wiki/Special:FilePath/Katsushika%20Hokusai%20Travellers%20passing%20through%20village.jpg",
      "thumb": "https://commons.wikimedia.org/wiki/Special:FilePath/Katsushika%20Hokusai%20Travellers%20passing%20through%20village.jpg?width=400",
      "title": "poem by Fujiwara no Michinobu",
      "source": "guimet",
      "tags": [
        "landscape"
      ]
    },
    {
      "img": "https://commons.wikimedia.org/wiki/Special:FilePath/Offering%20carrier-MA%204680-IMG%209502-gradient.jpg",
      "thumb": "https://commons.wikimedia.org/wiki/Special:FilePath/Offering%20carrier-MA%204680-IMG%209502-gradient.jpg?width=400",
      "title": "Offering carrier-MA 4680",
      "source": "guimet",
      "tags": [
        "landscape"
      ]
    },
    {
      "img": "https://commons.wikimedia.org/wiki/Special:FilePath/Hokusai%20au%20mus%C3%A9e%20Guimet%20%288285809552%29.jpg",
      "thumb": "https://commons.wikimedia.org/wiki/Special:FilePath/Hokusai%20au%20mus%C3%A9e%20Guimet%20%288285809552%29.jpg?width=400",
      "title": "poem by Tenji Tennō",
      "source": "guimet",
      "tags": [
        "landscape"
      ]
    },
    {
      "img": "https://commons.wikimedia.org/wiki/Special:FilePath/Hokusai%20au%20mus%C3%A9e%20Guimet%20%288288589067%29.jpg",
      "thumb": "https://commons.wikimedia.org/wiki/Special:FilePath/Hokusai%20au%20mus%C3%A9e%20Guimet%20%288288589067%29.jpg?width=400",
      "title": "poem by Kakinomoto Hitomaro",
      "source": "guimet",
      "tags": [
        "landscape"
      ]
    },
    {
      "img": "https://commons.wikimedia.org/wiki/Special:FilePath/Hokusai%20au%20mus%C3%A9e%20Guimet%20%288289711708%29.jpg",
      "thumb": "https://commons.wikimedia.org/wiki/Special:FilePath/Hokusai%20au%20mus%C3%A9e%20Guimet%20%288289711708%29.jpg?width=400",
      "title": "poem by Sarumaru Dayū",
      "source": "guimet",
      "tags": [
        "landscape"
      ]
    },
    {
      "img": "https://commons.wikimedia.org/wiki/Special:FilePath/Sarumaru-dayu.jpeg",
      "thumb": "https://commons.wikimedia.org/wiki/Special:FilePath/Sarumaru-dayu.jpeg?width=400",
      "title": "poem by Sarumaru Dayū",
      "source": "guimet",
      "tags": [
        "landscape"
      ]
    },
    {
      "img": "https://commons.wikimedia.org/wiki/Special:FilePath/Musician-MA%204681-IMG%209504-gradient.jpg",
      "thumb": "https://commons.wikimedia.org/wiki/Special:FilePath/Musician-MA%204681-IMG%209504-gradient.jpg?width=400",
      "title": "Musician-MA 4681",
      "source": "guimet",
      "tags": [
        "landscape"
      ]
    },
    {
      "img": "https://commons.wikimedia.org/wiki/Special:FilePath/Musician-MA%204682-IMG%209506-gradient.jpg",
      "thumb": "https://commons.wikimedia.org/wiki/Special:FilePath/Musician-MA%204682-IMG%209506-gradient.jpg?width=400",
      "title": "Musician-MA 4682",
      "source": "guimet",
      "tags": [
        "landscape"
      ]
    },
    {
      "img": "https://commons.wikimedia.org/wiki/Special:FilePath/Arrowhead-MA%203899-IMG%209458-gradient.jpg",
      "thumb": "https://commons.wikimedia.org/wiki/Special:FilePath/Arrowhead-MA%203899-IMG%209458-gradient.jpg?width=400",
      "title": "Arrowhead-MA 3899",
      "source": "guimet",
      "tags": [
        "landscape"
      ]
    },
    {
      "img": "https://commons.wikimedia.org/wiki/Special:FilePath/Paris%20-%20Mus%C3%A9e%20Guimet%20-%20MA%205949%20-%2020110601%20%281%29.jpg",
      "thumb": "https://commons.wikimedia.org/wiki/Special:FilePath/Paris%20-%20Mus%C3%A9e%20Guimet%20-%20MA%205949%20-%2020110601%20%281%29.jpg?width=400",
      "title": "Arhat assis",
      "source": "guimet",
      "tags": [
        "landscape"
      ]
    },
    {
      "img": "https://commons.wikimedia.org/wiki/Special:FilePath/Clothes%20ornaments-MA%206589-IMG%209476-gradient.jpg",
      "thumb": "https://commons.wikimedia.org/wiki/Special:FilePath/Clothes%20ornaments-MA%206589-IMG%209476-gradient.jpg?width=400",
      "title": "Clothes ornaments-MA 6589",
      "source": "guimet",
      "tags": [
        "landscape"
      ]
    },
    {
      "img": "https://commons.wikimedia.org/wiki/Special:FilePath/Clothes%20ornaments-MA%206836-IMG%209478-gradient.jpg",
      "thumb": "https://commons.wikimedia.org/wiki/Special:FilePath/Clothes%20ornaments-MA%206836-IMG%209478-gradient.jpg?width=400",
      "title": "Clothes ornaments-MA 6836",
      "source": "guimet",
      "tags": [
        "landscape"
      ]
    },
    {
      "img": "https://commons.wikimedia.org/wiki/Special:FilePath/Mirror-MA%20336-IMG%209092-gradient.jpg",
      "thumb": "https://commons.wikimedia.org/wiki/Special:FilePath/Mirror-MA%20336-IMG%209092-gradient.jpg?width=400",
      "title": "Mirror-MA 336",
      "source": "guimet",
      "tags": [
        "landscape"
      ]
    },
    {
      "img": "https://commons.wikimedia.org/wiki/Special:FilePath/Mirror-MA%207079-IMG%209090-gradient.jpg",
      "thumb": "https://commons.wikimedia.org/wiki/Special:FilePath/Mirror-MA%207079-IMG%209090-gradient.jpg?width=400",
      "title": "Mirror-MA 7079",
      "source": "guimet",
      "tags": [
        "landscape"
      ]
    },
    {
      "img": "https://commons.wikimedia.org/wiki/Special:FilePath/Mirror-MG%2015014-IMG%209556-gradient.jpg",
      "thumb": "https://commons.wikimedia.org/wiki/Special:FilePath/Mirror-MG%2015014-IMG%209556-gradient.jpg?width=400",
      "title": "Mirror-MG 15014",
      "source": "guimet",
      "tags": [
        "landscape"
      ]
    },
    {
      "img": "https://commons.wikimedia.org/wiki/Special:FilePath/Mirror-MA%201093-IMG%209558-gradient.jpg",
      "thumb": "https://commons.wikimedia.org/wiki/Special:FilePath/Mirror-MA%201093-IMG%209558-gradient.jpg?width=400",
      "title": "Mirror-MA 1093",
      "source": "guimet",
      "tags": [
        "landscape"
      ]
    },
    {
      "img": "https://commons.wikimedia.org/wiki/Special:FilePath/Poids%20de%20natte%20en%20forme%20de%20buffle%20couch%C3%A9.jpg",
      "thumb": "https://commons.wikimedia.org/wiki/Special:FilePath/Poids%20de%20natte%20en%20forme%20de%20buffle%20couch%C3%A9.jpg?width=400",
      "title": "Poids de natte en forme de buffle couché",
      "source": "guimet",
      "tags": [
        "architecture"
      ]
    },
    {
      "img": "https://commons.wikimedia.org/wiki/Special:FilePath/Paris%20-%20Mus%C3%A9e%20Guimet%208020.jpg",
      "thumb": "https://commons.wikimedia.org/wiki/Special:FilePath/Paris%20-%20Mus%C3%A9e%20Guimet%208020.jpg?width=400",
      "title": "head of bodhisattva",
      "source": "guimet",
      "tags": [
        "architecture"
      ]
    },
    {
      "img": "https://commons.wikimedia.org/wiki/Special:FilePath/Paris%20-%20Mus%C3%A9e%20Guimet%208090.jpg",
      "thumb": "https://commons.wikimedia.org/wiki/Special:FilePath/Paris%20-%20Mus%C3%A9e%20Guimet%208090.jpg?width=400",
      "title": "bodhisattva Avalokiteśvara",
      "source": "guimet",
      "tags": [
        "architecture"
      ]
    },
    {
      "img": "https://commons.wikimedia.org/wiki/Special:FilePath/Paris%20-%20Mus%C3%A9e%20Guimet%208281.jpg",
      "thumb": "https://commons.wikimedia.org/wiki/Special:FilePath/Paris%20-%20Mus%C3%A9e%20Guimet%208281.jpg?width=400",
      "title": "Vase with a hundred deer",
      "source": "guimet",
      "tags": [
        "architecture"
      ]
    },
    {
      "img": "https://commons.wikimedia.org/wiki/Special:FilePath/Paris%20-%20Mus%C3%A9e%20Guimet%208278.jpg",
      "thumb": "https://commons.wikimedia.org/wiki/Special:FilePath/Paris%20-%20Mus%C3%A9e%20Guimet%208278.jpg?width=400",
      "title": "Vase with figures and landscape",
      "source": "guimet",
      "tags": [
        "architecture"
      ]
    },
    {
      "img": "https://commons.wikimedia.org/wiki/Special:FilePath/Navire%20%C3%A0%20vapeur%20et%20%C3%A0%20aube%20-%20Expo%20Le%20Monde%20vu%20d%27Asie%20au%20Mus%C3%A9e%20Guimet.jpg",
      "thumb": "https://commons.wikimedia.org/wiki/Special:FilePath/Navire%20%C3%A0%20vapeur%20et%20%C3%A0%20aube%20-%20Expo%20Le%20Monde%20vu%20d%27Asie%20au%20Mus%C3%A9e%20Guimet.jpg?width=400",
      "title": "Navire à vapeur et à aubes",
      "source": "guimet",
      "tags": [
        "architecture"
      ]
    },
    {
      "img": "https://commons.wikimedia.org/wiki/Special:FilePath/Armure%20japonaise%20-%20Mus%C3%A9e%20Guimet%20-%20MA%208102%20-%20gradient.jpg",
      "thumb": "https://commons.wikimedia.org/wiki/Special:FilePath/Armure%20japonaise%20-%20Mus%C3%A9e%20Guimet%20-%20MA%208102%20-%20gradient.jpg?width=400",
      "title": "Samurai Armour - MA 8102",
      "source": "guimet",
      "tags": [
        "architecture"
      ]
    },
    {
      "img": "https://commons.wikimedia.org/wiki/Special:FilePath/Vue%20de%20l%27agencement%20int%C3%A9rieur%20d%27un%20cuirass%C3%A9%20allemand%20-%20expo%20Le%20Monde%20vu%20d%27Asie%20au%20Mus%C3%A9e%20Guimet%20-%20MA%206687.jpg",
      "thumb": "https://commons.wikimedia.org/wiki/Special:FilePath/Vue%20de%20l%27agencement%20int%C3%A9rieur%20d%27un%20cuirass%C3%A9%20allemand%20-%20expo%20Le%20Monde%20vu%20d%27Asie%20au%20Mus%C3%A9e%20Guimet%20-%20MA%206687.jpg?width=400",
      "title": "Vue de l'aménagement intérieur d'un cuirassé allemand",
      "source": "guimet",
      "tags": [
        "architecture"
      ]
    },
    {
      "img": "https://commons.wikimedia.org/wiki/Special:FilePath/Plat%20%C3%A0%20d%C3%A9cor%20de%20bateau%20hollandais%20-%20expo%20Le%20Monde%20vu%20d%27Asie%20au%20Mus%C3%A9e%20Guimet.jpg",
      "thumb": "https://commons.wikimedia.org/wiki/Special:FilePath/Plat%20%C3%A0%20d%C3%A9cor%20de%20bateau%20hollandais%20-%20expo%20Le%20Monde%20vu%20d%27Asie%20au%20Mus%C3%A9e%20Guimet.jpg?width=400",
      "title": "plat à décor de bateau hollandais",
      "source": "guimet",
      "tags": [
        "architecture"
      ]
    },
    {
      "img": "https://commons.wikimedia.org/wiki/Special:FilePath/Portraits%20d%27hommes%20et%20de%20femmes%20de%20tous%20pays%20-%20expo%20Le%20Monde%20vu%20d%27Asie%20au%20Mus%C3%A9e%20Guimet%20-%20MA%204516.jpg",
      "thumb": "https://commons.wikimedia.org/wiki/Special:FilePath/Portraits%20d%27hommes%20et%20de%20femmes%20de%20tous%20pays%20-%20expo%20Le%20Monde%20vu%20d%27Asie%20au%20Mus%C3%A9e%20Guimet%20-%20MA%204516.jpg?width=400",
      "title": "Portraits d'homme et de femmes de tous pays",
      "source": "guimet",
      "tags": [
        "architecture"
      ]
    },
    {
      "img": "https://commons.wikimedia.org/wiki/Special:FilePath/Anyang%20funerary%20bed%20%28reconstitution%20with%20gates%29.jpg",
      "thumb": "https://commons.wikimedia.org/wiki/Special:FilePath/Anyang%20funerary%20bed%20%28reconstitution%20with%20gates%29.jpg?width=400",
      "title": "Anyang funerary bed",
      "source": "guimet",
      "tags": [
        "architecture"
      ]
    },
    {
      "img": "https://commons.wikimedia.org/wiki/Special:FilePath/Veste%20d%27armes%20%28jimbaori%29%20-%20Mus%C3%A9e%20Guimet%20-%20MA%205761%20-%20gradient.jpg",
      "thumb": "https://commons.wikimedia.org/wiki/Special:FilePath/Veste%20d%27armes%20%28jimbaori%29%20-%20Mus%C3%A9e%20Guimet%20-%20MA%205761%20-%20gradient.jpg?width=400",
      "title": "Jinbaori MA 5761",
      "source": "guimet",
      "tags": [
        "architecture"
      ]
    },
    {
      "img": "https://commons.wikimedia.org/wiki/Special:FilePath/Coffre%20Nanban%20-%20Mus%C3%A9e%20Guimet%20-%20MA%205154%20-%20gradient.jpg",
      "thumb": "https://commons.wikimedia.org/wiki/Special:FilePath/Coffre%20Nanban%20-%20Mus%C3%A9e%20Guimet%20-%20MA%205154%20-%20gradient.jpg?width=400",
      "title": "Nanban Chest",
      "source": "guimet",
      "tags": [
        "architecture"
      ]
    },
    {
      "img": "https://commons.wikimedia.org/wiki/Special:FilePath/Pot%20%C3%A0%20th%C3%A9%20%28Natsume%29%20%C3%A0%20d%C3%A9cor%20d%27armoiries%20de%20la%20famille%20Tokugawa%20-%20Mus%C3%A9e%20Guimet%20-%20G3712.jpg",
      "thumb": "https://commons.wikimedia.org/wiki/Special:FilePath/Pot%20%C3%A0%20th%C3%A9%20%28Natsume%29%20%C3%A0%20d%C3%A9cor%20d%27armoiries%20de%20la%20famille%20Tokugawa%20-%20Mus%C3%A9e%20Guimet%20-%20G3712.jpg?width=400",
      "title": "pot à thé (natsume) à décor d'armoiries de la famille Tokugawa",
      "source": "guimet",
      "tags": [
        "architecture"
      ]
    },
    {
      "img": "https://commons.wikimedia.org/wiki/Special:FilePath/Shah%20Jahan%20and%20his%20four%20sons%20by%20Willem%20Schellinks%20end%20of%2017th%20century.jpg",
      "thumb": "https://commons.wikimedia.org/wiki/Special:FilePath/Shah%20Jahan%20and%20his%20four%20sons%20by%20Willem%20Schellinks%20end%20of%2017th%20century.jpg?width=400",
      "title": "Shah Jahan and his four sons",
      "source": "guimet",
      "tags": [
        "architecture"
      ]
    },
    {
      "img": "https://commons.wikimedia.org/wiki/Special:FilePath/Vase-EO%202891-IMG%209042-gradient.jpg",
      "thumb": "https://commons.wikimedia.org/wiki/Special:FilePath/Vase-EO%202891-IMG%209042-gradient.jpg?width=400",
      "title": "Vase-EO 2891",
      "source": "guimet",
      "tags": [
        "fashion"
      ]
    },
    {
      "img": "https://commons.wikimedia.org/wiki/Special:FilePath/Ewer-MA%206941-IMG%209139-gradient.jpg",
      "thumb": "https://commons.wikimedia.org/wiki/Special:FilePath/Ewer-MA%206941-IMG%209139-gradient.jpg?width=400",
      "title": "Ewer-MA 6941",
      "source": "guimet",
      "tags": [
        "fashion"
      ]
    },
    {
      "img": "https://commons.wikimedia.org/wiki/Special:FilePath/Garland%20and%20Cupids-AO%202920-IMG%208458-gradient.jpg",
      "thumb": "https://commons.wikimedia.org/wiki/Special:FilePath/Garland%20and%20Cupids-AO%202920-IMG%208458-gradient.jpg?width=400",
      "title": "garland and Cupids-AO 2920",
      "source": "guimet",
      "tags": [
        "fashion"
      ]
    },
    {
      "img": "https://commons.wikimedia.org/wiki/Special:FilePath/Servant-MA%206102-IMG%208708-gradient.jpg",
      "thumb": "https://commons.wikimedia.org/wiki/Special:FilePath/Servant-MA%206102-IMG%208708-gradient.jpg?width=400",
      "title": "Servant-MA 6102",
      "source": "guimet",
      "tags": [
        "fashion"
      ]
    },
    {
      "img": "https://commons.wikimedia.org/wiki/Special:FilePath/Boshanlu%20perfume%20burner-EO%202733-IMG%209430-gradient.jpg",
      "thumb": "https://commons.wikimedia.org/wiki/Special:FilePath/Boshanlu%20perfume%20burner-EO%202733-IMG%209430-gradient.jpg?width=400",
      "title": "Boshanlu perfume burner-EO 2733",
      "source": "guimet",
      "tags": [
        "fashion"
      ]
    },
    {
      "img": "https://commons.wikimedia.org/wiki/Special:FilePath/Brush%20pot-G%203497-IMG%209111-gradient.jpg",
      "thumb": "https://commons.wikimedia.org/wiki/Special:FilePath/Brush%20pot-G%203497-IMG%209111-gradient.jpg?width=400",
      "title": "Brush pot-G 3497",
      "source": "guimet",
      "tags": [
        "fashion"
      ]
    },
    {
      "img": "https://commons.wikimedia.org/wiki/Special:FilePath/Bi%20disk-MG%2018349-IMG%209533-gradient.jpg",
      "thumb": "https://commons.wikimedia.org/wiki/Special:FilePath/Bi%20disk-MG%2018349-IMG%209533-gradient.jpg?width=400",
      "title": "Bi disk-MG 18349",
      "source": "guimet",
      "tags": [
        "fashion"
      ]
    },
    {
      "img": "https://commons.wikimedia.org/wiki/Special:FilePath/Inro-Ladyfly%20on%20a%20spider%20web-EO%202226-IMG%208739-gradient.jpg",
      "thumb": "https://commons.wikimedia.org/wiki/Special:FilePath/Inro-Ladyfly%20on%20a%20spider%20web-EO%202226-IMG%208739-gradient.jpg?width=400",
      "title": "Inrō-Dragonfly on a spider web-EO 2226",
      "source": "guimet",
      "tags": [
        "fashion"
      ]
    },
    {
      "img": "https://commons.wikimedia.org/wiki/Special:FilePath/Woman%20carrying%20offerings-MA%204666-IMG%209498-gradient.jpg",
      "thumb": "https://commons.wikimedia.org/wiki/Special:FilePath/Woman%20carrying%20offerings-MA%204666-IMG%209498-gradient.jpg?width=400",
      "title": "Woman carrying offerings-MA 4666",
      "source": "guimet",
      "tags": [
        "fashion"
      ]
    },
    {
      "img": "https://commons.wikimedia.org/wiki/Special:FilePath/Kendi%20pot-G%204700-IMG%209112-gradient.jpg",
      "thumb": "https://commons.wikimedia.org/wiki/Special:FilePath/Kendi%20pot-G%204700-IMG%209112-gradient.jpg?width=400",
      "title": "Kendi pot-G 4700",
      "source": "guimet",
      "tags": [
        "fashion"
      ]
    },
    {
      "img": "https://commons.wikimedia.org/wiki/Special:FilePath/Ram-shaped%20lamp-EO%201582-IMG%209441-gradient.jpg",
      "thumb": "https://commons.wikimedia.org/wiki/Special:FilePath/Ram-shaped%20lamp-EO%201582-IMG%209441-gradient.jpg?width=400",
      "title": "Ram-shaped lamp-EO 1582",
      "source": "guimet",
      "tags": [
        "fashion"
      ]
    },
    {
      "img": "https://commons.wikimedia.org/wiki/Special:FilePath/Pot-MA%203986-IMG%209226-gradient.jpg",
      "thumb": "https://commons.wikimedia.org/wiki/Special:FilePath/Pot-MA%203986-IMG%209226-gradient.jpg?width=400",
      "title": "Pot-MA 3986",
      "source": "guimet",
      "tags": [
        "fashion"
      ]
    },
    {
      "img": "https://commons.wikimedia.org/wiki/Special:FilePath/Small%20spherical%20bottle-MA%203983-small%20spherical%20bottle-MA%203983-IMG%209222-gradient.jpg",
      "thumb": "https://commons.wikimedia.org/wiki/Special:FilePath/Small%20spherical%20bottle-MA%203983-small%20spherical%20bottle-MA%203983-IMG%209222-gradient.jpg?width=400",
      "title": "Small spherical bottle-MA 3983",
      "source": "guimet",
      "tags": [
        "fashion"
      ]
    },
    {
      "img": "https://commons.wikimedia.org/wiki/Special:FilePath/Courtier-MA%206104-IMG%208710-gradient.jpg",
      "thumb": "https://commons.wikimedia.org/wiki/Special:FilePath/Courtier-MA%206104-IMG%208710-gradient.jpg?width=400",
      "title": "Courtier-MA 6104",
      "source": "guimet",
      "tags": [
        "fashion"
      ]
    },
    {
      "img": "https://commons.wikimedia.org/wiki/Special:FilePath/Court%20lady%20Guimet%20MA6105.jpg",
      "thumb": "https://commons.wikimedia.org/wiki/Special:FilePath/Court%20lady%20Guimet%20MA6105.jpg?width=400",
      "title": "Courtier-MA 6105",
      "source": "guimet",
      "tags": [
        "fashion"
      ]
    },
    {
      "img": "https://commons.wikimedia.org/wiki/Special:FilePath/Court%20lady%20with%20hair%20bun%20Guimet%20MA6106%20n01.jpg",
      "thumb": "https://commons.wikimedia.org/wiki/Special:FilePath/Court%20lady%20with%20hair%20bun%20Guimet%20MA6106%20n01.jpg?width=400",
      "title": "Courtier-MA 6106",
      "source": "guimet",
      "tags": [
        "fashion"
      ]
    },
    {
      "img": "https://commons.wikimedia.org/wiki/Special:FilePath/Female%20polo%20player%20Guimet%20MA6116.jpg",
      "thumb": "https://commons.wikimedia.org/wiki/Special:FilePath/Female%20polo%20player%20Guimet%20MA6116.jpg?width=400",
      "title": "Female polo player-MA 6116",
      "source": "guimet",
      "tags": [
        "fashion"
      ]
    },
    {
      "img": "https://commons.wikimedia.org/wiki/Special:FilePath/Vase%20Song%20dynasty-MA%204113-IMG%209127-gradient.jpg",
      "thumb": "https://commons.wikimedia.org/wiki/Special:FilePath/Vase%20Song%20dynasty-MA%204113-IMG%209127-gradient.jpg?width=400",
      "title": "Vase Song dynasty-MA 4113",
      "source": "guimet",
      "tags": [
        "fashion"
      ]
    },
    {
      "img": "https://commons.wikimedia.org/wiki/Special:FilePath/Dou%20cup-MA%203047-IMG%209407-gradient.jpg",
      "thumb": "https://commons.wikimedia.org/wiki/Special:FilePath/Dou%20cup-MA%203047-IMG%209407-gradient.jpg?width=400",
      "title": "Dou cup-MA 3047",
      "source": "guimet",
      "tags": [
        "fashion"
      ]
    },
    {
      "img": "https://commons.wikimedia.org/wiki/Special:FilePath/Lotus%20ornated%20ewer-MA%205972-IMG%209102-gradient.jpg",
      "thumb": "https://commons.wikimedia.org/wiki/Special:FilePath/Lotus%20ornated%20ewer-MA%205972-IMG%209102-gradient.jpg?width=400",
      "title": "Lotus ornated ewer-MA 5972",
      "source": "guimet",
      "tags": [
        "fashion"
      ]
    },
    {
      "img": "https://commons.wikimedia.org/wiki/Special:FilePath/Votive%20stupa-MA%201175-IMG%208675-gradient.jpg",
      "thumb": "https://commons.wikimedia.org/wiki/Special:FilePath/Votive%20stupa-MA%201175-IMG%208675-gradient.jpg?width=400",
      "title": "Votive stupa-MA 1175",
      "source": "guimet",
      "tags": [
        "fashion"
      ]
    },
    {
      "img": "https://commons.wikimedia.org/wiki/Special:FilePath/Lotus%20decorated%20plate-G%201815-IMG%209236-gradient.jpg",
      "thumb": "https://commons.wikimedia.org/wiki/Special:FilePath/Lotus%20decorated%20plate-G%201815-IMG%209236-gradient.jpg?width=400",
      "title": "Lotus decorated plate-G 1815",
      "source": "guimet",
      "tags": [
        "fashion"
      ]
    },
    {
      "img": "https://commons.wikimedia.org/wiki/Special:FilePath/Gui%20vase-MA%206-IMG%209400-gradient.jpg",
      "thumb": "https://commons.wikimedia.org/wiki/Special:FilePath/Gui%20vase-MA%206-IMG%209400-gradient.jpg?width=400",
      "title": "Gui vase-MA 6",
      "source": "guimet",
      "tags": [
        "fashion"
      ]
    },
    {
      "img": "https://commons.wikimedia.org/wiki/Special:FilePath/Crossbow%20receiver-MA%20694-IMG%209453-gradient.jpg",
      "thumb": "https://commons.wikimedia.org/wiki/Special:FilePath/Crossbow%20receiver-MA%20694-IMG%209453-gradient.jpg?width=400",
      "title": "Crossbow receiver-MA 694",
      "source": "guimet",
      "tags": [
        "fashion"
      ]
    },
    {
      "img": "https://commons.wikimedia.org/wiki/Special:FilePath/Crossbow%20mechanism-MA%203061-IMG%209447-gradient.jpg",
      "thumb": "https://commons.wikimedia.org/wiki/Special:FilePath/Crossbow%20mechanism-MA%203061-IMG%209447-gradient.jpg?width=400",
      "title": "Crossbow mechanism-MA 3061",
      "source": "guimet",
      "tags": [
        "fashion"
      ]
    },
    {
      "img": "https://commons.wikimedia.org/wiki/Special:FilePath/Cavalier%20%C3%A0%20l%27oiseau.jpg",
      "thumb": "https://commons.wikimedia.org/wiki/Special:FilePath/Cavalier%20%C3%A0%20l%27oiseau.jpg?width=400",
      "title": "Mounted falconer-MA 6114",
      "source": "guimet",
      "tags": [
        "nature"
      ]
    },
    {
      "img": "https://commons.wikimedia.org/wiki/Special:FilePath/Meiping%20vase%20dragon%20Guimet%20G1211.jpg",
      "thumb": "https://commons.wikimedia.org/wiki/Special:FilePath/Meiping%20vase%20dragon%20Guimet%20G1211.jpg?width=400",
      "title": "Vase meiping à décor de dragons",
      "source": "guimet",
      "tags": [
        "nature"
      ]
    },
    {
      "img": "https://commons.wikimedia.org/wiki/Special:FilePath/Bhairava%20%28mus%C3%A9e%20Guimet%29%20%288602869201%29.jpg",
      "thumb": "https://commons.wikimedia.org/wiki/Special:FilePath/Bhairava%20%28mus%C3%A9e%20Guimet%29%20%288602869201%29.jpg?width=400",
      "title": "Shiva Mask. Bhairava",
      "source": "guimet",
      "tags": [
        "nature"
      ]
    },
    {
      "img": "https://commons.wikimedia.org/wiki/Special:FilePath/Vase%20bouteille%20%28mus%C3%A9e%20Guimet%2C%20Paris%29%20%2810876361736%29.jpg",
      "thumb": "https://commons.wikimedia.org/wiki/Special:FilePath/Vase%20bouteille%20%28mus%C3%A9e%20Guimet%2C%20Paris%29%20%2810876361736%29.jpg?width=400",
      "title": "Vase bouteille à décor de fleurs et oiseaux",
      "source": "guimet",
      "tags": [
        "nature"
      ]
    },
    {
      "img": "https://commons.wikimedia.org/wiki/Special:FilePath/Harunobu%20Kanzan%20et%20Jittoku.JPG",
      "thumb": "https://commons.wikimedia.org/wiki/Special:FilePath/Harunobu%20Kanzan%20et%20Jittoku.JPG?width=400",
      "title": "a mitate (parody) of Kanzan and Jittoku, the well known Chinese Buddhist monks",
      "source": "guimet",
      "tags": [
        "nature"
      ]
    },
    {
      "img": "https://commons.wikimedia.org/wiki/Special:FilePath/Dou%20cup-MA%205922-IMG%209410-gradient.jpg",
      "thumb": "https://commons.wikimedia.org/wiki/Special:FilePath/Dou%20cup-MA%205922-IMG%209410-gradient.jpg?width=400",
      "title": "Dou cup-MA 5922",
      "source": "guimet",
      "tags": [
        "nature"
      ]
    },
    {
      "img": "https://commons.wikimedia.org/wiki/Special:FilePath/Ewer-MA%205657-IMG%209098-gradient.jpg",
      "thumb": "https://commons.wikimedia.org/wiki/Special:FilePath/Ewer-MA%205657-IMG%209098-gradient.jpg?width=400",
      "title": "Ewer-MA 5657",
      "source": "guimet",
      "tags": [
        "nature"
      ]
    },
    {
      "img": "https://commons.wikimedia.org/wiki/Special:FilePath/Ding%20tripod%20vase-MA%203879-IMG%209387-gradient.jpg",
      "thumb": "https://commons.wikimedia.org/wiki/Special:FilePath/Ding%20tripod%20vase-MA%203879-IMG%209387-gradient.jpg?width=400",
      "title": "Ding tripod vase-MA 3879",
      "source": "guimet",
      "tags": [
        "nature"
      ]
    },
    {
      "img": "https://commons.wikimedia.org/wiki/Special:FilePath/Ding%20tripod%20vase-MA%20555-IMG%209389-gradient.jpg",
      "thumb": "https://commons.wikimedia.org/wiki/Special:FilePath/Ding%20tripod%20vase-MA%20555-IMG%209389-gradient.jpg?width=400",
      "title": "Ding tripod vase-MA 555",
      "source": "guimet",
      "tags": [
        "nature"
      ]
    },
    {
      "img": "https://commons.wikimedia.org/wiki/Special:FilePath/Fantastic%20bird-MG%2017727-IMG%208677-gradient.jpg",
      "thumb": "https://commons.wikimedia.org/wiki/Special:FilePath/Fantastic%20bird-MG%2017727-IMG%208677-gradient.jpg?width=400",
      "title": "Fantastic bird-MG 17727",
      "source": "guimet",
      "tags": [
        "nature"
      ]
    },
    {
      "img": "https://commons.wikimedia.org/wiki/Special:FilePath/Yaksa%20demon%20genie-EO%201081-IMG%208681-gradient.jpg",
      "thumb": "https://commons.wikimedia.org/wiki/Special:FilePath/Yaksa%20demon%20genie-EO%201081-IMG%208681-gradient.jpg?width=400",
      "title": "Head of a Yaksha demon",
      "source": "guimet",
      "tags": [
        "nature"
      ]
    },
    {
      "img": "https://commons.wikimedia.org/wiki/Special:FilePath/Fantastic%20animal-EO%201076-IMG%208684-gradient.jpg",
      "thumb": "https://commons.wikimedia.org/wiki/Special:FilePath/Fantastic%20animal-EO%201076-IMG%208684-gradient.jpg?width=400",
      "title": "Fantastic animal-EO 1076",
      "source": "guimet",
      "tags": [
        "nature"
      ]
    },
    {
      "img": "https://commons.wikimedia.org/wiki/Special:FilePath/Fantastic%20animal-MG%2023558-IMG%208690-gradient.jpg",
      "thumb": "https://commons.wikimedia.org/wiki/Special:FilePath/Fantastic%20animal-MG%2023558-IMG%208690-gradient.jpg?width=400",
      "title": "Fantastic animal-MG 23558",
      "source": "guimet",
      "tags": [
        "nature"
      ]
    },
    {
      "img": "https://commons.wikimedia.org/wiki/Special:FilePath/Archerer%20ring-MA%203871-IMG%209449-gradient.jpg",
      "thumb": "https://commons.wikimedia.org/wiki/Special:FilePath/Archerer%20ring-MA%203871-IMG%209449-gradient.jpg?width=400",
      "title": "Archerer ring-MA 3871",
      "source": "guimet",
      "tags": [
        "nature"
      ]
    },
    {
      "img": "https://commons.wikimedia.org/wiki/Special:FilePath/Archerer%20ring-MA%203872-IMG%209450-gradient.jpg",
      "thumb": "https://commons.wikimedia.org/wiki/Special:FilePath/Archerer%20ring-MA%203872-IMG%209450-gradient.jpg?width=400",
      "title": "Archerer ring-MA 3872",
      "source": "guimet",
      "tags": [
        "nature"
      ]
    },
    {
      "img": "https://commons.wikimedia.org/wiki/Special:FilePath/Gui-like%20container-AA%2079-IMG%209421-gradient.jpg",
      "thumb": "https://commons.wikimedia.org/wiki/Special:FilePath/Gui-like%20container-AA%2079-IMG%209421-gradient.jpg?width=400",
      "title": "Gui-like container-AA 79",
      "source": "guimet",
      "tags": [
        "nature"
      ]
    },
    {
      "img": "https://commons.wikimedia.org/wiki/Special:FilePath/Falconer-MA%206125-IMG%209267-gradient.jpg",
      "thumb": "https://commons.wikimedia.org/wiki/Special:FilePath/Falconer-MA%206125-IMG%209267-gradient.jpg?width=400",
      "title": "falconer-MA 6125",
      "source": "guimet",
      "tags": [
        "nature"
      ]
    },
    {
      "img": "https://commons.wikimedia.org/wiki/Special:FilePath/Gui%20vase-MA%201586-IMG%209403-gradient.jpg",
      "thumb": "https://commons.wikimedia.org/wiki/Special:FilePath/Gui%20vase-MA%201586-IMG%209403-gradient.jpg?width=400",
      "title": "Gui vase-MA 1586",
      "source": "guimet",
      "tags": [
        "nature"
      ]
    },
    {
      "img": "https://commons.wikimedia.org/wiki/Special:FilePath/Pensive%20Bodhisattva%20Guimet%20MA3913.jpg",
      "thumb": "https://commons.wikimedia.org/wiki/Special:FilePath/Pensive%20Bodhisattva%20Guimet%20MA3913.jpg?width=400",
      "title": "Bodhisattva assis",
      "source": "guimet",
      "tags": [
        "nature"
      ]
    },
    {
      "img": "https://commons.wikimedia.org/wiki/Special:FilePath/Wang%20Hui.%20detail.Mus%C3%A9e%20Guimet.jpg",
      "thumb": "https://commons.wikimedia.org/wiki/Special:FilePath/Wang%20Hui.%20detail.Mus%C3%A9e%20Guimet.jpg?width=400",
      "title": "Forêt sous le givre par un soir clair",
      "source": "guimet",
      "tags": [
        "nature"
      ]
    },
    {
      "img": "https://commons.wikimedia.org/wiki/Special:FilePath/Paysage%20de%20montagne%20%28d%C3%A9tail%29%20par%20Liu%20Jue.jpg",
      "thumb": "https://commons.wikimedia.org/wiki/Special:FilePath/Paysage%20de%20montagne%20%28d%C3%A9tail%29%20par%20Liu%20Jue.jpg?width=400",
      "title": "Retraite dans la montagne",
      "source": "guimet",
      "tags": [
        "nature"
      ]
    },
    {
      "img": "https://commons.wikimedia.org/wiki/Special:FilePath/Paris%20-%20Mus%C3%A9e%20Guimet%20-%20Chien%20assis%20-%20MA%205945.jpg",
      "thumb": "https://commons.wikimedia.org/wiki/Special:FilePath/Paris%20-%20Mus%C3%A9e%20Guimet%20-%20Chien%20assis%20-%20MA%205945.jpg?width=400",
      "title": "Chien assis",
      "source": "guimet",
      "tags": [
        "nature"
      ]
    },
    {
      "img": "https://commons.wikimedia.org/wiki/Special:FilePath/Utamaro%20%28c.%201794%E2%80%9395%29%20Hokkoku%20Goshiki-zumi%20-%20Kiri%20no%20Musume.jpg",
      "thumb": "https://commons.wikimedia.org/wiki/Special:FilePath/Utamaro%20%28c.%201794%E2%80%9395%29%20Hokkoku%20Goshiki-zumi%20-%20Kiri%20no%20Musume.jpg?width=400",
      "title": "Kiri no Musume",
      "source": "guimet",
      "tags": [
        "nature"
      ]
    },
    {
      "img": "https://commons.wikimedia.org/wiki/Special:FilePath/Qazak%20pay%20tribute%20to%20Qianlong.jpg",
      "thumb": "https://commons.wikimedia.org/wiki/Special:FilePath/Qazak%20pay%20tribute%20to%20Qianlong.jpg?width=400",
      "title": "Qazaq présentant leur tribut de chevaux à l'empereur Qianlong",
      "source": "guimet",
      "tags": [
        "nature"
      ]
    },
    {
      "img": "https://commons.wikimedia.org/wiki/Special:FilePath/Head%20of%20a%20Bodhisattva%20Guimet%20MA2533.jpg",
      "thumb": "https://commons.wikimedia.org/wiki/Special:FilePath/Head%20of%20a%20Bodhisattva%20Guimet%20MA2533.jpg?width=400",
      "title": "Tête de bodhisattva",
      "source": "guimet",
      "tags": [
        "nature"
      ]
    },
    {
      "img": "https://commons.wikimedia.org/wiki/Special:FilePath/Vase%20Song%20dynasty-MA%203021-IMG%209131-gradient.jpg",
      "thumb": "https://commons.wikimedia.org/wiki/Special:FilePath/Vase%20Song%20dynasty-MA%203021-IMG%209131-gradient.jpg?width=400",
      "title": "Vase Song dynasty-MA 3021",
      "source": "guimet",
      "tags": [
        "abstract"
      ]
    },
    {
      "img": "https://commons.wikimedia.org/wiki/Special:FilePath/Sitted%20Bodhisattva-MG%2015363-IMG%208952-gradient.jpg",
      "thumb": "https://commons.wikimedia.org/wiki/Special:FilePath/Sitted%20Bodhisattva-MG%2015363-IMG%208952-gradient.jpg?width=400",
      "title": "Sitted Bodhisattva-MG 15363",
      "source": "guimet",
      "tags": [
        "abstract"
      ]
    },
    {
      "img": "https://commons.wikimedia.org/wiki/Special:FilePath/Plate%20ornated%20with%20phoenix-MA%207075-IMG%209076-gradient.jpg",
      "thumb": "https://commons.wikimedia.org/wiki/Special:FilePath/Plate%20ornated%20with%20phoenix-MA%207075-IMG%209076-gradient.jpg?width=400",
      "title": "Plate ornated with phoenix-MA 7075",
      "source": "guimet",
      "tags": [
        "abstract"
      ]
    },
    {
      "img": "https://commons.wikimedia.org/wiki/Special:FilePath/Yase%20Onna-EO%201586-IMG%208857-gradient.jpg",
      "thumb": "https://commons.wikimedia.org/wiki/Special:FilePath/Yase%20Onna-EO%201586-IMG%208857-gradient.jpg?width=400",
      "title": "Yase Onna-EO 1586",
      "source": "guimet",
      "tags": [
        "abstract"
      ]
    },
    {
      "img": "https://commons.wikimedia.org/wiki/Special:FilePath/Yaseotoko-MA%201247-IMG%208880-gadient.jpg",
      "thumb": "https://commons.wikimedia.org/wiki/Special:FilePath/Yaseotoko-MA%201247-IMG%208880-gadient.jpg?width=400",
      "title": "Yase Otoko-MA 1247",
      "source": "guimet",
      "tags": [
        "abstract"
      ]
    },
    {
      "img": "https://commons.wikimedia.org/wiki/Special:FilePath/Tsuba-EO%20302-IMG%208798-gradient.jpg",
      "thumb": "https://commons.wikimedia.org/wiki/Special:FilePath/Tsuba-EO%20302-IMG%208798-gradient.jpg?width=400",
      "title": "Tsuba-EO 302",
      "source": "guimet",
      "tags": [
        "abstract"
      ]
    },
    {
      "img": "https://commons.wikimedia.org/wiki/Special:FilePath/Voyage%20dans%20le%20Sud%20de%20l%27empereur%20Kangxi%20par%20le%20peintre%20chinois%20Wang%20Hui%201632-1717.jpg",
      "thumb": "https://commons.wikimedia.org/wiki/Special:FilePath/Voyage%20dans%20le%20Sud%20de%20l%27empereur%20Kangxi%20par%20le%20peintre%20chinois%20Wang%20Hui%201632-1717.jpg?width=400",
      "title": "The Kangxi Emperor's Southern Inspection Tour, Scroll Two: Pingyuan to Ji'nan",
      "source": "guimet",
      "tags": [
        "abstract"
      ]
    },
    {
      "img": "https://commons.wikimedia.org/wiki/Special:FilePath/Tsuba-EO%20325-IMG%208793-gradient.jpg",
      "thumb": "https://commons.wikimedia.org/wiki/Special:FilePath/Tsuba-EO%20325-IMG%208793-gradient.jpg?width=400",
      "title": "tsuba-EO 325",
      "source": "guimet",
      "tags": [
        "abstract"
      ]
    },
    {
      "img": "https://commons.wikimedia.org/wiki/Special:FilePath/Tsuba-EO%20330-IMG%208827-gradient.jpg",
      "thumb": "https://commons.wikimedia.org/wiki/Special:FilePath/Tsuba-EO%20330-IMG%208827-gradient.jpg?width=400",
      "title": "tsuba-EO 330",
      "source": "guimet",
      "tags": [
        "abstract"
      ]
    },
    {
      "img": "https://commons.wikimedia.org/wiki/Special:FilePath/Tsuba-EO%20342-IMG%208805-gradient.jpg",
      "thumb": "https://commons.wikimedia.org/wiki/Special:FilePath/Tsuba-EO%20342-IMG%208805-gradient.jpg?width=400",
      "title": "tsuba-EO 342",
      "source": "guimet",
      "tags": [
        "abstract"
      ]
    },
    {
      "img": "https://commons.wikimedia.org/wiki/Special:FilePath/Tsuba-EO%20611-IMG%208799-gradient.jpg",
      "thumb": "https://commons.wikimedia.org/wiki/Special:FilePath/Tsuba-EO%20611-IMG%208799-gradient.jpg?width=400",
      "title": "tsuba-EO 611",
      "source": "guimet",
      "tags": [
        "abstract"
      ]
    },
    {
      "img": "https://commons.wikimedia.org/wiki/Special:FilePath/Tsuba-MG%209334-IMG%208837-gradient.jpg",
      "thumb": "https://commons.wikimedia.org/wiki/Special:FilePath/Tsuba-MG%209334-IMG%208837-gradient.jpg?width=400",
      "title": "tsuba-MG 9334",
      "source": "guimet",
      "tags": [
        "abstract"
      ]
    },
    {
      "img": "https://commons.wikimedia.org/wiki/Special:FilePath/Tsuba-EO%202368-IMG%208824-gradient.jpg",
      "thumb": "https://commons.wikimedia.org/wiki/Special:FilePath/Tsuba-EO%202368-IMG%208824-gradient.jpg?width=400",
      "title": "tsuba-EO 2368",
      "source": "guimet",
      "tags": [
        "abstract"
      ]
    },
    {
      "img": "https://commons.wikimedia.org/wiki/Special:FilePath/Tsuba-EO%202369-IMG%208822-gradient.jpg",
      "thumb": "https://commons.wikimedia.org/wiki/Special:FilePath/Tsuba-EO%202369-IMG%208822-gradient.jpg?width=400",
      "title": "tsuba-EO 2369",
      "source": "guimet",
      "tags": [
        "abstract"
      ]
    },
    {
      "img": "https://commons.wikimedia.org/wiki/Special:FilePath/Tsuba-EO%202373-IMG%208835-gradient.jpg",
      "thumb": "https://commons.wikimedia.org/wiki/Special:FilePath/Tsuba-EO%202373-IMG%208835-gradient.jpg?width=400",
      "title": "tsuba-EO 2373",
      "source": "guimet",
      "tags": [
        "abstract"
      ]
    },
    {
      "img": "https://commons.wikimedia.org/wiki/Special:FilePath/Tsuba-EO%202721-IMG%208797-gradient.jpg",
      "thumb": "https://commons.wikimedia.org/wiki/Special:FilePath/Tsuba-EO%202721-IMG%208797-gradient.jpg?width=400",
      "title": "tsuba-EO 2721",
      "source": "guimet",
      "tags": [
        "abstract"
      ]
    },
    {
      "img": "https://commons.wikimedia.org/wiki/Special:FilePath/Tsuba-EO%202729-IMG%208796-gradient.jpg",
      "thumb": "https://commons.wikimedia.org/wiki/Special:FilePath/Tsuba-EO%202729-IMG%208796-gradient.jpg?width=400",
      "title": "tsuba-EO 2729",
      "source": "guimet",
      "tags": [
        "abstract"
      ]
    },
    {
      "img": "https://commons.wikimedia.org/wiki/Special:FilePath/Tsuba-EO%202922-IMG%208831-gradient.jpg",
      "thumb": "https://commons.wikimedia.org/wiki/Special:FilePath/Tsuba-EO%202922-IMG%208831-gradient.jpg?width=400",
      "title": "tsuba-EO 2922",
      "source": "guimet",
      "tags": [
        "abstract"
      ]
    },
    {
      "img": "https://commons.wikimedia.org/wiki/Special:FilePath/Tsuba-EO%203107-IMG%208794-gradient.jpg",
      "thumb": "https://commons.wikimedia.org/wiki/Special:FilePath/Tsuba-EO%203107-IMG%208794-gradient.jpg?width=400",
      "title": "tsuba-EO 3107",
      "source": "guimet",
      "tags": [
        "abstract"
      ]
    },
    {
      "img": "https://commons.wikimedia.org/wiki/Special:FilePath/Tsuba-EO%203146-IMG%208802-gradient.jpg",
      "thumb": "https://commons.wikimedia.org/wiki/Special:FilePath/Tsuba-EO%203146-IMG%208802-gradient.jpg?width=400",
      "title": "tsuba-EO 3146",
      "source": "guimet",
      "tags": [
        "abstract"
      ]
    },
    {
      "img": "https://commons.wikimedia.org/wiki/Special:FilePath/Tsuba-EO%20334-IMG%208828-gradient.jpg",
      "thumb": "https://commons.wikimedia.org/wiki/Special:FilePath/Tsuba-EO%20334-IMG%208828-gradient.jpg?width=400",
      "title": "tsuba-EO 334",
      "source": "guimet",
      "tags": [
        "abstract"
      ]
    },
    {
      "img": "https://commons.wikimedia.org/wiki/Special:FilePath/Tsuba-MG%2025474-IMG%208795-gradient.jpg",
      "thumb": "https://commons.wikimedia.org/wiki/Special:FilePath/Tsuba-MG%2025474-IMG%208795-gradient.jpg?width=400",
      "title": "tsuba-MG 25474",
      "source": "guimet",
      "tags": [
        "abstract"
      ]
    },
    {
      "img": "https://commons.wikimedia.org/wiki/Special:FilePath/Tsuba-MG%206162-IMG%208832-gradient.jpg",
      "thumb": "https://commons.wikimedia.org/wiki/Special:FilePath/Tsuba-MG%206162-IMG%208832-gradient.jpg?width=400",
      "title": "tsuba-MG 6162",
      "source": "guimet",
      "tags": [
        "abstract"
      ]
    },
    {
      "img": "https://commons.wikimedia.org/wiki/Special:FilePath/Chorei%20Beshimi-MA%203234-IMG%208867-gradient.jpg",
      "thumb": "https://commons.wikimedia.org/wiki/Special:FilePath/Chorei%20Beshimi-MA%203234-IMG%208867-gradient.jpg?width=400",
      "title": "Chorei Beshimi-MA 3234",
      "source": "guimet",
      "tags": [
        "abstract"
      ]
    },
    {
      "img": "https://commons.wikimedia.org/wiki/Special:FilePath/Chujo-MA%203256-IMG%208896-gradient.jpg",
      "thumb": "https://commons.wikimedia.org/wiki/Special:FilePath/Chujo-MA%203256-IMG%208896-gradient.jpg?width=400",
      "title": "Chūjō-MA 3256",
      "source": "guimet",
      "tags": [
        "texture"
      ]
    },
    {
      "img": "https://commons.wikimedia.org/wiki/Special:FilePath/Hannya-MA%203231-IMG%208875-gradient.jpg",
      "thumb": "https://commons.wikimedia.org/wiki/Special:FilePath/Hannya-MA%203231-IMG%208875-gradient.jpg?width=400",
      "title": "Hannya-MA 3231",
      "source": "guimet",
      "tags": [
        "texture"
      ]
    },
    {
      "img": "https://commons.wikimedia.org/wiki/Special:FilePath/Bodhisattva%20Avalokitesvara-MA%20533-IMG%208663-gradient.jpg",
      "thumb": "https://commons.wikimedia.org/wiki/Special:FilePath/Bodhisattva%20Avalokitesvara-MA%20533-IMG%208663-gradient.jpg?width=400",
      "title": "Bodhisattva Avalokitesvara",
      "source": "guimet",
      "tags": [
        "texture"
      ]
    },
    {
      "img": "https://commons.wikimedia.org/wiki/Special:FilePath/Divinite-bandteay%20kdei.jpg",
      "thumb": "https://commons.wikimedia.org/wiki/Special:FilePath/Divinite-bandteay%20kdei.jpg?width=400",
      "title": "Divinité féminine",
      "source": "guimet",
      "tags": [
        "texture"
      ]
    },
    {
      "img": "https://commons.wikimedia.org/wiki/Special:FilePath/Buddha-preah%20kahn.jpg",
      "thumb": "https://commons.wikimedia.org/wiki/Special:FilePath/Buddha-preah%20kahn.jpg?width=400",
      "title": "Buddha",
      "source": "guimet",
      "tags": [
        "texture"
      ]
    },
    {
      "img": "https://commons.wikimedia.org/wiki/Special:FilePath/Lion-MG%2021162-IMG%208567-gradient.jpg",
      "thumb": "https://commons.wikimedia.org/wiki/Special:FilePath/Lion-MG%2021162-IMG%208567-gradient.jpg?width=400",
      "title": "Lion",
      "source": "guimet",
      "tags": [
        "texture"
      ]
    },
    {
      "img": "https://commons.wikimedia.org/wiki/Special:FilePath/Bodhisattva-MG%2017085-IMG%208649-gradient.jpg",
      "thumb": "https://commons.wikimedia.org/wiki/Special:FilePath/Bodhisattva-MG%2017085-IMG%208649-gradient.jpg?width=400",
      "title": "Bodhisattva Avalokitesvara",
      "source": "guimet",
      "tags": [
        "texture"
      ]
    },
    {
      "img": "https://commons.wikimedia.org/wiki/Special:FilePath/Coupe%20Mazarin%20Mus%C3%A9e%20Guimet%2030122016%202.jpg",
      "thumb": "https://commons.wikimedia.org/wiki/Special:FilePath/Coupe%20Mazarin%20Mus%C3%A9e%20Guimet%2030122016%202.jpg?width=400",
      "title": "Coupe Mazarin",
      "source": "guimet",
      "tags": [
        "texture"
      ]
    },
    {
      "img": "https://commons.wikimedia.org/wiki/Special:FilePath/Dinastia%20qing%2C%20coppia%20di%20armadi%20a%20due%20ante%2C%201662-1722%20ca.%2001.JPG",
      "thumb": "https://commons.wikimedia.org/wiki/Special:FilePath/Dinastia%20qing%2C%20coppia%20di%20armadi%20a%20due%20ante%2C%201662-1722%20ca.%2001.JPG?width=400",
      "title": "Chinese cupboard",
      "source": "guimet",
      "tags": [
        "texture"
      ]
    },
    {
      "img": "https://commons.wikimedia.org/wiki/Special:FilePath/Wang%20Hui6.jpg",
      "thumb": "https://commons.wikimedia.org/wiki/Special:FilePath/Wang%20Hui6.jpg?width=400",
      "title": "Hut in the Autumn Rain",
      "source": "guimet",
      "tags": [
        "texture"
      ]
    },
    {
      "img": "https://commons.wikimedia.org/wiki/Special:FilePath/Flickr%20-%20dalbera%20-%20Statue%20de%20l%27Arhat%20Tamrabhadra%20%28mus%C3%A9e%20Guimet%29.jpg",
      "thumb": "https://commons.wikimedia.org/wiki/Special:FilePath/Flickr%20-%20dalbera%20-%20Statue%20de%20l%27Arhat%20Tamrabhadra%20%28mus%C3%A9e%20Guimet%29.jpg?width=400",
      "title": "Arhat Tamrabhadra (musée Guimet)",
      "source": "guimet",
      "tags": [
        "texture"
      ]
    },
    {
      "img": "https://commons.wikimedia.org/wiki/Special:FilePath/Dunhuang%20Mara%20Budda.jpg",
      "thumb": "https://commons.wikimedia.org/wiki/Special:FilePath/Dunhuang%20Mara%20Budda.jpg?width=400",
      "title": "Mara experiences the Buddha",
      "source": "guimet",
      "tags": [
        "texture"
      ]
    },
    {
      "img": "https://commons.wikimedia.org/wiki/Special:FilePath/Battle%20scene-MG%2017046-IMG%208453-gradient.jpg",
      "thumb": "https://commons.wikimedia.org/wiki/Special:FilePath/Battle%20scene-MG%2017046-IMG%208453-gradient.jpg?width=400",
      "title": "Battle scene",
      "source": "guimet",
      "tags": [
        "texture"
      ]
    },
    {
      "img": "https://commons.wikimedia.org/wiki/Special:FilePath/Portrait%20de%20Cho%20Man-Yong.jpg",
      "thumb": "https://commons.wikimedia.org/wiki/Special:FilePath/Portrait%20de%20Cho%20Man-Yong.jpg?width=400",
      "title": "Portrait of Cho Man-Yong",
      "source": "guimet",
      "tags": [
        "texture"
      ]
    },
    {
      "img": "https://commons.wikimedia.org/wiki/Special:FilePath/Guimet%20shitao%20monts%20jinting.jpg",
      "thumb": "https://commons.wikimedia.org/wiki/Special:FilePath/Guimet%20shitao%20monts%20jinting.jpg?width=400",
      "title": "Jing Ting Mountain in Autumn",
      "source": "guimet",
      "tags": [
        "texture"
      ]
    },
    {
      "img": "https://commons.wikimedia.org/wiki/Special:FilePath/Four-statuette%20set%20depicting%20musicians-MA%204667-MA%204668-MA%204669-MA%204670-IMG%209488-90-92-93-gradient.jpg",
      "thumb": "https://commons.wikimedia.org/wiki/Special:FilePath/Four-statuette%20set%20depicting%20musicians-MA%204667-MA%204668-MA%204669-MA%204670-IMG%209488-90-92-93-gradient.jpg?width=400",
      "title": "Four-statuette set depicting musicians",
      "source": "guimet",
      "tags": [
        "texture"
      ]
    },
    {
      "img": "https://commons.wikimedia.org/wiki/Special:FilePath/Huang%20pendant-MG%2018438-IMG%209534-gradient.jpg",
      "thumb": "https://commons.wikimedia.org/wiki/Special:FilePath/Huang%20pendant-MG%2018438-IMG%209534-gradient.jpg?width=400",
      "title": "Huang pendant-MG 18438",
      "source": "guimet",
      "tags": [
        "texture"
      ]
    },
    {
      "img": "https://commons.wikimedia.org/wiki/Special:FilePath/Female%20bust-MG%2021210-IMG%208574-gradient.jpg",
      "thumb": "https://commons.wikimedia.org/wiki/Special:FilePath/Female%20bust-MG%2021210-IMG%208574-gradient.jpg?width=400",
      "title": "Female bust-MG 21210",
      "source": "guimet",
      "tags": [
        "texture"
      ]
    },
    {
      "img": "https://commons.wikimedia.org/wiki/Special:FilePath/Guzheng%20player-MA%206319-IMG%209539-gradient.jpg",
      "thumb": "https://commons.wikimedia.org/wiki/Special:FilePath/Guzheng%20player-MA%206319-IMG%209539-gradient.jpg?width=400",
      "title": "Guzheng player-MA 6319",
      "source": "guimet",
      "tags": [
        "texture"
      ]
    },
    {
      "img": "https://commons.wikimedia.org/wiki/Special:FilePath/Horse-MA%202547-IMG%209544-gradient.jpg",
      "thumb": "https://commons.wikimedia.org/wiki/Special:FilePath/Horse-MA%202547-IMG%209544-gradient.jpg?width=400",
      "title": "Horse-MA 2547",
      "source": "guimet",
      "tags": [
        "texture"
      ]
    },
    {
      "img": "https://commons.wikimedia.org/wiki/Special:FilePath/Cup-MA%204048-IMG%209234-gradient.jpg",
      "thumb": "https://commons.wikimedia.org/wiki/Special:FilePath/Cup-MA%204048-IMG%209234-gradient.jpg?width=400",
      "title": "Cup-MA 4048",
      "source": "guimet",
      "tags": [
        "texture"
      ]
    },
    {
      "img": "https://commons.wikimedia.org/wiki/Special:FilePath/Spouted%20vase-EO%202903-IMG%209039-gradient.jpg",
      "thumb": "https://commons.wikimedia.org/wiki/Special:FilePath/Spouted%20vase-EO%202903-IMG%209039-gradient.jpg?width=400",
      "title": "Spouted vase",
      "source": "guimet",
      "tags": [
        "texture"
      ]
    },
    {
      "img": "https://commons.wikimedia.org/wiki/Special:FilePath/Two%20guardian%20genies-MA%204663-MA%204664-IMG%209470-gradient.jpg",
      "thumb": "https://commons.wikimedia.org/wiki/Special:FilePath/Two%20guardian%20genies-MA%204663-MA%204664-IMG%209470-gradient.jpg?width=400",
      "title": "Two guardian genies-MA 4663-MA 4664",
      "source": "guimet",
      "tags": [
        "texture"
      ]
    },
    {
      "img": "https://commons.wikimedia.org/wiki/Special:FilePath/Vase%20Song%20dynasty-MA%202931-IMG%209133-gradient.jpg",
      "thumb": "https://commons.wikimedia.org/wiki/Special:FilePath/Vase%20Song%20dynasty-MA%202931-IMG%209133-gradient.jpg?width=400",
      "title": "Vase Song dynasty-MA 2931",
      "source": "guimet",
      "tags": [
        "texture"
      ]
    },
    {
      "img": "https://commons.wikimedia.org/wiki/Special:FilePath/Two%20dancers-MA%206122a-b-IMG%208713-gradient.jpg",
      "thumb": "https://commons.wikimedia.org/wiki/Special:FilePath/Two%20dancers-MA%206122a-b-IMG%208713-gradient.jpg?width=400",
      "title": "Two dancers-MA 6122a-b",
      "source": "guimet",
      "tags": [
        "texture"
      ]
    },
    {
      "img": "https://commons.wikimedia.org/wiki/Special:FilePath/Tobide-MA%203238-IMG%208871-gradient.jpg",
      "thumb": "https://commons.wikimedia.org/wiki/Special:FilePath/Tobide-MA%203238-IMG%208871-gradient.jpg?width=400",
      "title": "Tobide-MA 3238",
      "source": "guimet",
      "tags": [
        "light"
      ]
    },
    {
      "img": "https://commons.wikimedia.org/wiki/Special:FilePath/Maya%20Devi-MA%201779-IMG%208431-gradient.jpg",
      "thumb": "https://commons.wikimedia.org/wiki/Special:FilePath/Maya%20Devi-MA%201779-IMG%208431-gradient.jpg?width=400",
      "title": "Māyā Devī-MA 1779",
      "source": "guimet",
      "tags": [
        "light"
      ]
    },
    {
      "img": "https://commons.wikimedia.org/wiki/Special:FilePath/Nepal%2C%20la%20regina%20maya%20devi%20d%C3%A0%20vita%20al%20principe%20siddharta%2C%20futuro%20buddha%20sakyamuni%2C%201810%20ca..JPG",
      "thumb": "https://commons.wikimedia.org/wiki/Special:FilePath/Nepal%2C%20la%20regina%20maya%20devi%20d%C3%A0%20vita%20al%20principe%20siddharta%2C%20futuro%20buddha%20sakyamuni%2C%201810%20ca..JPG?width=400",
      "title": "Māyā Devī-MA 1779",
      "source": "guimet",
      "tags": [
        "light"
      ]
    },
    {
      "img": "https://commons.wikimedia.org/wiki/Special:FilePath/Sravasti%20miracle-MG%2017478-IMG%208565-gradient.jpg",
      "thumb": "https://commons.wikimedia.org/wiki/Special:FilePath/Sravasti%20miracle-MG%2017478-IMG%208565-gradient.jpg?width=400",
      "title": "Sravasti miracle-MG 17478",
      "source": "guimet",
      "tags": [
        "light"
      ]
    },
    {
      "img": "https://commons.wikimedia.org/wiki/Special:FilePath/Landscape%20under%20snow%20in%20the%20style%20of%20Ry%C5%8D%20Kai-MA%20634-IMG%209968.JPG",
      "thumb": "https://commons.wikimedia.org/wiki/Special:FilePath/Landscape%20under%20snow%20in%20the%20style%20of%20Ry%C5%8D%20Kai-MA%20634-IMG%209968.JPG?width=400",
      "title": "landscape under snow in the style of Ryō Kai",
      "source": "guimet",
      "tags": [
        "light"
      ]
    },
    {
      "img": "https://commons.wikimedia.org/wiki/Special:FilePath/Landscape%20under%20snow%20mountain%20village-Shiokawa%20Bunrin-MA%20635-IMG%209974.JPG",
      "thumb": "https://commons.wikimedia.org/wiki/Special:FilePath/Landscape%20under%20snow%20mountain%20village-Shiokawa%20Bunrin-MA%20635-IMG%209974.JPG?width=400",
      "title": "Landscape under snow: mountain village",
      "source": "guimet",
      "tags": [
        "light"
      ]
    },
    {
      "img": "https://commons.wikimedia.org/wiki/Special:FilePath/Reishonyo%20basker%20seller-Kogetsu%20Shurin-EO%20826-IMG%209980-81.JPG",
      "thumb": "https://commons.wikimedia.org/wiki/Special:FilePath/Reishonyo%20basker%20seller-Kogetsu%20Shurin-EO%20826-IMG%209980-81.JPG?width=400",
      "title": "Reishōnyo, the basker seller",
      "source": "guimet",
      "tags": [
        "light"
      ]
    },
    {
      "img": "https://commons.wikimedia.org/wiki/Special:FilePath/Sitting%20lion-MA%204214-IMG%200025-gradient.jpg",
      "thumb": "https://commons.wikimedia.org/wiki/Special:FilePath/Sitting%20lion-MA%204214-IMG%200025-gradient.jpg?width=400",
      "title": "figurine of a sitting lion",
      "source": "guimet",
      "tags": [
        "light"
      ]
    },
    {
      "img": "https://commons.wikimedia.org/wiki/Special:FilePath/Bodhisattva%20sitting%20on%20lotus-IO%201354-IMG%208598-gradient.jpg",
      "thumb": "https://commons.wikimedia.org/wiki/Special:FilePath/Bodhisattva%20sitting%20on%20lotus-IO%201354-IMG%208598-gradient.jpg?width=400",
      "title": "Bodhisattva sitting on lotus-IO 1354",
      "source": "guimet",
      "tags": [
        "light"
      ]
    },
    {
      "img": "https://commons.wikimedia.org/wiki/Special:FilePath/Bodhisattva%20sitting%20on%20lotus-MG%2015258-IMG%208947-gradient.jpg",
      "thumb": "https://commons.wikimedia.org/wiki/Special:FilePath/Bodhisattva%20sitting%20on%20lotus-MG%2015258-IMG%208947-gradient.jpg?width=400",
      "title": "Bodhisattva sitting on lotus-MG 15258",
      "source": "guimet",
      "tags": [
        "light"
      ]
    },
    {
      "img": "https://commons.wikimedia.org/wiki/Special:FilePath/Cup-G%20958-IMG%209095-gradient.jpg",
      "thumb": "https://commons.wikimedia.org/wiki/Special:FilePath/Cup-G%20958-IMG%209095-gradient.jpg?width=400",
      "title": "Cup-G 958",
      "source": "guimet",
      "tags": [
        "shadow"
      ]
    },
    {
      "img": "https://commons.wikimedia.org/wiki/Special:FilePath/Cup-MA%204797-IMG%209183-gradient.jpg",
      "thumb": "https://commons.wikimedia.org/wiki/Special:FilePath/Cup-MA%204797-IMG%209183-gradient.jpg?width=400",
      "title": "Cup-MA 4797",
      "source": "guimet",
      "tags": [
        "shadow"
      ]
    },
    {
      "img": "https://commons.wikimedia.org/wiki/Special:FilePath/Zeng-AA%2077-IMG%209416-gradient.jpg",
      "thumb": "https://commons.wikimedia.org/wiki/Special:FilePath/Zeng-AA%2077-IMG%209416-gradient.jpg?width=400",
      "title": "Zeng-AA 77",
      "source": "guimet",
      "tags": [
        "shadow"
      ]
    },
    {
      "img": "https://commons.wikimedia.org/wiki/Special:FilePath/Courtier%20MA%204718-IMG%209527-gradient.jpg",
      "thumb": "https://commons.wikimedia.org/wiki/Special:FilePath/Courtier%20MA%204718-IMG%209527-gradient.jpg?width=400",
      "title": "Courtier-MA 4718",
      "source": "guimet",
      "tags": [
        "shadow"
      ]
    },
    {
      "img": "https://commons.wikimedia.org/wiki/Special:FilePath/Perfume%20burner-MA%204195-IMG%209164-gradient.jpg",
      "thumb": "https://commons.wikimedia.org/wiki/Special:FilePath/Perfume%20burner-MA%204195-IMG%209164-gradient.jpg?width=400",
      "title": "Perfume burner-MA 4195",
      "source": "guimet",
      "tags": [
        "shadow"
      ]
    },
    {
      "img": "https://commons.wikimedia.org/wiki/Special:FilePath/Landscape%20with%20Rocks%20and%20Pine%20Forest-AA%20281-IMG%208993.JPG",
      "thumb": "https://commons.wikimedia.org/wiki/Special:FilePath/Landscape%20with%20Rocks%20and%20Pine%20Forest-AA%20281-IMG%208993.JPG?width=400",
      "title": "Landscape with Rocks and Pine Forest-AA 281",
      "source": "guimet",
      "tags": [
        "shadow"
      ]
    },
    {
      "img": "https://commons.wikimedia.org/wiki/Special:FilePath/Qing-era%20vase-G%202774-IMG%209114-gradient.jpg",
      "thumb": "https://commons.wikimedia.org/wiki/Special:FilePath/Qing-era%20vase-G%202774-IMG%209114-gradient.jpg?width=400",
      "title": "Qing-era vase-G 2774",
      "source": "guimet",
      "tags": [
        "shadow"
      ]
    },
    {
      "img": "https://commons.wikimedia.org/wiki/Special:FilePath/Head%20of%20Buddha-MG%2012688-IMG%208527-gradient.jpg",
      "thumb": "https://commons.wikimedia.org/wiki/Special:FilePath/Head%20of%20Buddha-MG%2012688-IMG%208527-gradient.jpg?width=400",
      "title": "Head of Buddha-MG 12688",
      "source": "guimet",
      "tags": [
        "shadow"
      ]
    },
    {
      "img": "https://commons.wikimedia.org/wiki/Special:FilePath/Head%20of%20Buddha-MG%2017437-IMG%208526-gradient.jpg",
      "thumb": "https://commons.wikimedia.org/wiki/Special:FilePath/Head%20of%20Buddha-MG%2017437-IMG%208526-gradient.jpg?width=400",
      "title": "Head of Buddha-MG 17437",
      "source": "guimet",
      "tags": [
        "shadow"
      ]
    },
    {
      "img": "https://commons.wikimedia.org/wiki/Special:FilePath/Manbi-EO%202161-IMG%208891-gradient.jpg",
      "thumb": "https://commons.wikimedia.org/wiki/Special:FilePath/Manbi-EO%202161-IMG%208891-gradient.jpg?width=400",
      "title": "manbi-EO 2161",
      "source": "guimet",
      "tags": [
        "shadow"
      ]
    },
    {
      "img": "https://commons.wikimedia.org/wiki/Special:FilePath/Oji-MA%203233-IMG%208863-gradient.jpg",
      "thumb": "https://commons.wikimedia.org/wiki/Special:FilePath/Oji-MA%203233-IMG%208863-gradient.jpg?width=400",
      "title": "oji-MA 3233",
      "source": "guimet",
      "tags": [
        "shadow"
      ]
    },
    {
      "img": "https://commons.wikimedia.org/wiki/Special:FilePath/Yaseonna-EO%201550-IMG%208889-gradient.jpg",
      "thumb": "https://commons.wikimedia.org/wiki/Special:FilePath/Yaseonna-EO%201550-IMG%208889-gradient.jpg?width=400",
      "title": "yaseonna-EO 1550",
      "source": "guimet",
      "tags": [
        "shadow"
      ]
    },
    {
      "img": "https://commons.wikimedia.org/wiki/Special:FilePath/Yaseotoko-MA%203234-IMG%208861-gradient.jpg",
      "thumb": "https://commons.wikimedia.org/wiki/Special:FilePath/Yaseotoko-MA%203234-IMG%208861-gradient.jpg?width=400",
      "title": "yaseotoko-MA 3234",
      "source": "guimet",
      "tags": [
        "shadow"
      ]
    },
    {
      "img": "https://commons.wikimedia.org/wiki/Special:FilePath/Portable%20stele-MSD%2076-IMG%208668-gradient.jpg",
      "thumb": "https://commons.wikimedia.org/wiki/Special:FilePath/Portable%20stele-MSD%2076-IMG%208668-gradient.jpg?width=400",
      "title": "Portable stele-MSD 76",
      "source": "guimet",
      "tags": [
        "shadow"
      ]
    },
    {
      "img": "https://commons.wikimedia.org/wiki/Special:FilePath/Tsuba-EO%203191-IMG%209009-gradient.jpg",
      "thumb": "https://commons.wikimedia.org/wiki/Special:FilePath/Tsuba-EO%203191-IMG%209009-gradient.jpg?width=400",
      "title": "Tsuba-EO 3191",
      "source": "guimet",
      "tags": [
        "shadow"
      ]
    },
    {
      "img": "https://commons.wikimedia.org/wiki/Special:FilePath/Tsuba-EO%202708-IMG%209012-gradient.jpg",
      "thumb": "https://commons.wikimedia.org/wiki/Special:FilePath/Tsuba-EO%202708-IMG%209012-gradient.jpg?width=400",
      "title": "Tsuba-EO 2708",
      "source": "guimet",
      "tags": [
        "shadow"
      ]
    },
    {
      "img": "https://commons.wikimedia.org/wiki/Special:FilePath/Tsuba-EO%203216-IMG%209011-gradient.jpg",
      "thumb": "https://commons.wikimedia.org/wiki/Special:FilePath/Tsuba-EO%203216-IMG%209011-gradient.jpg?width=400",
      "title": "Tsuba-EO 3216",
      "source": "guimet",
      "tags": [
        "shadow"
      ]
    },
    {
      "img": "https://commons.wikimedia.org/wiki/Special:FilePath/Tsuba-MG%209580-IMG%209010-gradient.jpg",
      "thumb": "https://commons.wikimedia.org/wiki/Special:FilePath/Tsuba-MG%209580-IMG%209010-gradient.jpg?width=400",
      "title": "Tsuba-MG 9580",
      "source": "guimet",
      "tags": [
        "shadow"
      ]
    },
    {
      "img": "https://commons.wikimedia.org/wiki/Special:FilePath/Plate-MG%205324-IMG%209013.JPG",
      "thumb": "https://commons.wikimedia.org/wiki/Special:FilePath/Plate-MG%205324-IMG%209013.JPG?width=400",
      "title": "Plate-MG 5324",
      "source": "guimet",
      "tags": [
        "shadow"
      ]
    },
    {
      "img": "https://commons.wikimedia.org/wiki/Special:FilePath/Bodhisattva-MA%2012183-IMG%209374-gradient.jpg",
      "thumb": "https://commons.wikimedia.org/wiki/Special:FilePath/Bodhisattva-MA%2012183-IMG%209374-gradient.jpg?width=400",
      "title": "Bodhisattva-MA 12183",
      "source": "guimet",
      "tags": [
        "shadow"
      ]
    },
    {
      "img": "https://commons.wikimedia.org/wiki/Special:FilePath/Terracotta%20cup-Charles%20Varat%20unnumbered-IMG%208972-gradient.jpg",
      "thumb": "https://commons.wikimedia.org/wiki/Special:FilePath/Terracotta%20cup-Charles%20Varat%20unnumbered-IMG%208972-gradient.jpg?width=400",
      "title": "Terracotta cup-Charles Varat unnumbered",
      "source": "guimet",
      "tags": [
        "shadow"
      ]
    },
    {
      "img": "https://commons.wikimedia.org/wiki/Special:FilePath/Somen-MA%2012143%208853-gradient.jpg",
      "thumb": "https://commons.wikimedia.org/wiki/Special:FilePath/Somen-MA%2012143%208853-gradient.jpg?width=400",
      "title": "Somen-MA 12143",
      "source": "guimet",
      "tags": [
        "shadow"
      ]
    },
    {
      "img": "https://commons.wikimedia.org/wiki/Special:FilePath/Ornated%20architecture%20element-MG%2023728-IMG%208621-gradient.jpg",
      "thumb": "https://commons.wikimedia.org/wiki/Special:FilePath/Ornated%20architecture%20element-MG%2023728-IMG%208621-gradient.jpg?width=400",
      "title": "Ornated architecture element-MG 23728",
      "source": "guimet",
      "tags": [
        "shadow"
      ]
    },
    {
      "img": "https://commons.wikimedia.org/wiki/Special:FilePath/Sitted%20buddha%20meditating-EO%201116-IMG%208662-gradient.jpg",
      "thumb": "https://commons.wikimedia.org/wiki/Special:FilePath/Sitted%20buddha%20meditating-EO%201116-IMG%208662-gradient.jpg?width=400",
      "title": "Sitted buddha meditating-EO 1116",
      "source": "guimet",
      "tags": [
        "shadow"
      ]
    },
    {
      "img": "https://commons.wikimedia.org/wiki/Special:FilePath/Standing%20Buddha-MA%206284-IMG%208459-gradient.jpg",
      "thumb": "https://commons.wikimedia.org/wiki/Special:FilePath/Standing%20Buddha-MA%206284-IMG%208459-gradient.jpg?width=400",
      "title": "Standing Buddha-MA 6284",
      "source": "guimet",
      "tags": [
        "shadow"
      ]
    },
    {
      "img": "https://commons.wikimedia.org/wiki/Special:FilePath/Arrowhead-Unnumbered-IMG%208919-gradient.jpg",
      "thumb": "https://commons.wikimedia.org/wiki/Special:FilePath/Arrowhead-Unnumbered-IMG%208919-gradient.jpg?width=400",
      "title": "stone arrowhead of the late Korean Bronze age",
      "source": "guimet",
      "tags": [
        "color"
      ]
    },
    {
      "img": "https://commons.wikimedia.org/wiki/Special:FilePath/Harness%20plaque-MA%20913-IMG%208935-gradient.jpg",
      "thumb": "https://commons.wikimedia.org/wiki/Special:FilePath/Harness%20plaque-MA%20913-IMG%208935-gradient.jpg?width=400",
      "title": "Harness plaque-MA 913",
      "source": "guimet",
      "tags": [
        "color"
      ]
    },
    {
      "img": "https://commons.wikimedia.org/wiki/Special:FilePath/Bottle-MG%2014067-IMG%209074-gradient.jpg",
      "thumb": "https://commons.wikimedia.org/wiki/Special:FilePath/Bottle-MG%2014067-IMG%209074-gradient.jpg?width=400",
      "title": "Bottle-MG 14067",
      "source": "guimet",
      "tags": [
        "color"
      ]
    },
    {
      "img": "https://commons.wikimedia.org/wiki/Special:FilePath/Cup-G3492-IMG%209072-gradient.jpg",
      "thumb": "https://commons.wikimedia.org/wiki/Special:FilePath/Cup-G3492-IMG%209072-gradient.jpg?width=400",
      "title": "Cup-G 3492",
      "source": "guimet",
      "tags": [
        "color"
      ]
    },
    {
      "img": "https://commons.wikimedia.org/wiki/Special:FilePath/Dragon%20decorated%20jar-G%204926-IMG%209069-gradient.jpg",
      "thumb": "https://commons.wikimedia.org/wiki/Special:FilePath/Dragon%20decorated%20jar-G%204926-IMG%209069-gradient.jpg?width=400",
      "title": "Dragon decorated jar-G 4926",
      "source": "guimet",
      "tags": [
        "color"
      ]
    },
    {
      "img": "https://commons.wikimedia.org/wiki/Special:FilePath/Ewer-G%202687-IMG%209075.jpg",
      "thumb": "https://commons.wikimedia.org/wiki/Special:FilePath/Ewer-G%202687-IMG%209075.jpg?width=400",
      "title": "Ewer-G 2687",
      "source": "guimet",
      "tags": [
        "color"
      ]
    },
    {
      "img": "https://commons.wikimedia.org/wiki/Special:FilePath/Bowl-G%203229-IMG%209096-gradient.jpg",
      "thumb": "https://commons.wikimedia.org/wiki/Special:FilePath/Bowl-G%203229-IMG%209096-gradient.jpg?width=400",
      "title": "Bowl-G 3229",
      "source": "guimet",
      "tags": [
        "color"
      ]
    },
    {
      "img": "https://commons.wikimedia.org/wiki/Special:FilePath/Ewer-G%205088-IMG%209100-gradient.jpg",
      "thumb": "https://commons.wikimedia.org/wiki/Special:FilePath/Ewer-G%205088-IMG%209100-gradient.jpg?width=400",
      "title": "Ewer-G 5088",
      "source": "guimet",
      "tags": [
        "color"
      ]
    },
    {
      "img": "https://commons.wikimedia.org/wiki/Special:FilePath/Flower-shaped%20cup-AA%2099-IMG%209134.jpg",
      "thumb": "https://commons.wikimedia.org/wiki/Special:FilePath/Flower-shaped%20cup-AA%2099-IMG%209134.jpg?width=400",
      "title": "flower-shaped cup-AA 99",
      "source": "guimet",
      "tags": [
        "color"
      ]
    },
    {
      "img": "https://commons.wikimedia.org/wiki/Special:FilePath/Ceramic%20pillow-MA%204271-IMG%209261-gradient.jpg",
      "thumb": "https://commons.wikimedia.org/wiki/Special:FilePath/Ceramic%20pillow-MA%204271-IMG%209261-gradient.jpg?width=400",
      "title": "Ceramic pillow-MA 4271",
      "source": "guimet",
      "tags": [
        "color"
      ]
    },
    {
      "img": "https://commons.wikimedia.org/wiki/Special:FilePath/Ceramic%20pillow-MA%206204-IMG%209258.JPG",
      "thumb": "https://commons.wikimedia.org/wiki/Special:FilePath/Ceramic%20pillow-MA%206204-IMG%209258.JPG?width=400",
      "title": "Ceramic pillow-MA 6204",
      "source": "guimet",
      "tags": [
        "color"
      ]
    },
    {
      "img": "https://commons.wikimedia.org/wiki/Special:FilePath/Chinese%20statuette-Guimet%20museum-IMG%208721-gradient.jpg",
      "thumb": "https://commons.wikimedia.org/wiki/Special:FilePath/Chinese%20statuette-Guimet%20museum-IMG%208721-gradient.jpg?width=400",
      "title": "Chinese statuette of a courtier",
      "source": "guimet",
      "tags": [
        "color"
      ]
    },
    {
      "img": "https://commons.wikimedia.org/wiki/Special:FilePath/Dinastia%20tang%2C%20caravaniere%20straniero%2C%20cina%20del%20nord%2C%20vii%20sec.JPG",
      "thumb": "https://commons.wikimedia.org/wiki/Special:FilePath/Dinastia%20tang%2C%20caravaniere%20straniero%2C%20cina%20del%20nord%2C%20vii%20sec.JPG?width=400",
      "title": "Statuette of a foreign caravaneer-MA 6107",
      "source": "guimet",
      "tags": [
        "color"
      ]
    },
    {
      "img": "https://commons.wikimedia.org/wiki/Special:FilePath/Bodhisattva%20Avalokite%C5%9Bvara%20Guimet%20MG18284%20n01.jpg",
      "thumb": "https://commons.wikimedia.org/wiki/Special:FilePath/Bodhisattva%20Avalokite%C5%9Bvara%20Guimet%20MG18284%20n01.jpg?width=400",
      "title": "Bodhisattva Avalokitesvara-MG 18284",
      "source": "guimet",
      "tags": [
        "color"
      ]
    },
    {
      "img": "https://commons.wikimedia.org/wiki/Special:FilePath/Tang%20Musiciennes%20assises.jpeg",
      "thumb": "https://commons.wikimedia.org/wiki/Special:FilePath/Tang%20Musiciennes%20assises.jpeg?width=400",
      "title": "Three statuettes of musicians of the Tang dynasty",
      "source": "guimet",
      "tags": [
        "color"
      ]
    },
    {
      "img": "https://commons.wikimedia.org/wiki/Special:FilePath/Dinastia%20tang%20%28o%20fine%20sui%29%2C%20cammello%20che%20si%20alza%2C%20cina%20del%20nord%2C%20600-650%20ca..JPG",
      "thumb": "https://commons.wikimedia.org/wiki/Special:FilePath/Dinastia%20tang%20%28o%20fine%20sui%29%2C%20cammello%20che%20si%20alza%2C%20cina%20del%20nord%2C%20600-650%20ca..JPG?width=400",
      "title": "Statuette of a Bactrian camel-MA 6842",
      "source": "guimet",
      "tags": [
        "color"
      ]
    },
    {
      "img": "https://commons.wikimedia.org/wiki/Special:FilePath/Escultura%20china%20Guimet%2005.JPG",
      "thumb": "https://commons.wikimedia.org/wiki/Special:FilePath/Escultura%20china%20Guimet%2005.JPG?width=400",
      "title": "Seated monk-MA 6997",
      "source": "guimet",
      "tags": [
        "color"
      ]
    },
    {
      "img": "https://commons.wikimedia.org/wiki/Special:FilePath/Cheval%20capar%C3%A7onn%C3%A9e%20chine%20du%20nord%20Vs%20terre%20cuite.JPG",
      "thumb": "https://commons.wikimedia.org/wiki/Special:FilePath/Cheval%20capar%C3%A7onn%C3%A9e%20chine%20du%20nord%20Vs%20terre%20cuite.JPG?width=400",
      "title": "Caparisoned horse-MA 3917",
      "source": "guimet",
      "tags": [
        "color"
      ]
    },
    {
      "img": "https://commons.wikimedia.org/wiki/Special:FilePath/Dinastia%20han%20posteriore%2C%20testa%20di%20cavallo%2C%20sichuan%2C%20I-III%20sec.JPG",
      "thumb": "https://commons.wikimedia.org/wiki/Special:FilePath/Dinastia%20han%20posteriore%2C%20testa%20di%20cavallo%2C%20sichuan%2C%20I-III%20sec.JPG?width=400",
      "title": "Horse head-MA 4905",
      "source": "guimet",
      "tags": [
        "color"
      ]
    },
    {
      "img": "https://commons.wikimedia.org/wiki/Special:FilePath/Cheval%20blanc%20selle%20chine%20du%20nord.JPG",
      "thumb": "https://commons.wikimedia.org/wiki/Special:FilePath/Cheval%20blanc%20selle%20chine%20du%20nord.JPG?width=400",
      "title": "Statuette of a saddled white horse",
      "source": "guimet",
      "tags": [
        "color"
      ]
    },
    {
      "img": "https://commons.wikimedia.org/wiki/Special:FilePath/Dinastia%20tang%2C%20giocatrici%20di%20polo%2C%20cina%20del%20nord%2C%20700-750%20ca..JPG",
      "thumb": "https://commons.wikimedia.org/wiki/Special:FilePath/Dinastia%20tang%2C%20giocatrici%20di%20polo%2C%20cina%20del%20nord%2C%20700-750%20ca..JPG?width=400",
      "title": "Polo players-MA 6116-MA 6121",
      "source": "guimet",
      "tags": [
        "color"
      ]
    },
    {
      "img": "https://commons.wikimedia.org/wiki/Special:FilePath/Dinastia%20tang%2C%20palafreniere%20straniero%2C%20cina%20del%20nord%2C%20VII%20sec.JPG",
      "thumb": "https://commons.wikimedia.org/wiki/Special:FilePath/Dinastia%20tang%2C%20palafreniere%20straniero%2C%20cina%20del%20nord%2C%20VII%20sec.JPG?width=400",
      "title": "Foreign groom-MA 6108",
      "source": "guimet",
      "tags": [
        "color"
      ]
    },
    {
      "img": "https://commons.wikimedia.org/wiki/Special:FilePath/Dinastia%20tang%2C%20cavallo%20e%20palafreniere%20straniero%2C%20cina%20del%20nord%2C%20VIII%20sec%2001.JPG",
      "thumb": "https://commons.wikimedia.org/wiki/Special:FilePath/Dinastia%20tang%2C%20cavallo%20e%20palafreniere%20straniero%2C%20cina%20del%20nord%2C%20VIII%20sec%2001.JPG?width=400",
      "title": "Horse and foreign groom-MA 6865",
      "source": "guimet",
      "tags": [
        "color"
      ]
    },
    {
      "img": "https://commons.wikimedia.org/wiki/Special:FilePath/Dinastia%20tang%2C%20cavalliere%20suonatore%2C%20henan%2C%20700-715%20ca..JPG",
      "thumb": "https://commons.wikimedia.org/wiki/Special:FilePath/Dinastia%20tang%2C%20cavalliere%20suonatore%2C%20henan%2C%20700-715%20ca..JPG?width=400",
      "title": "Statuette of a mounted musician-MA 3991",
      "source": "guimet",
      "tags": [
        "color"
      ]
    },
    {
      "img": "https://commons.wikimedia.org/wiki/Special:FilePath/Cer%C3%A1mica%20Tang%20Guimet%2012.JPG",
      "thumb": "https://commons.wikimedia.org/wiki/Special:FilePath/Cer%C3%A1mica%20Tang%20Guimet%2012.JPG?width=400",
      "title": "sancai statuette of a sitted  woman holding a bird",
      "source": "guimet",
      "tags": [
        "color"
      ]
    },
    {
      "img": "https://commons.wikimedia.org/wiki/Special:FilePath/Hashi%20Hime-MA%203244-IMG%208883-gradient.jpg",
      "thumb": "https://commons.wikimedia.org/wiki/Special:FilePath/Hashi%20Hime-MA%203244-IMG%208883-gradient.jpg?width=400",
      "title": "Hashi Hime-MA 3244",
      "source": "guimet",
      "tags": [
        "pattern"
      ]
    },
    {
      "img": "https://commons.wikimedia.org/wiki/Special:FilePath/Kasshiki-EO%201603-IMG%208899-gradient.jpg",
      "thumb": "https://commons.wikimedia.org/wiki/Special:FilePath/Kasshiki-EO%201603-IMG%208899-gradient.jpg?width=400",
      "title": "Kasshiki-EO 1603",
      "source": "guimet",
      "tags": [
        "pattern"
      ]
    },
    {
      "img": "https://commons.wikimedia.org/wiki/Special:FilePath/Plat%20%C3%A0%20d%C3%A9cor%20d%27%C3%89cossais%20-%20Expo%20Le%20Monde%20vu%20d%27Asie%20au%20Mus%C3%A9e%20Guimet.jpg",
      "thumb": "https://commons.wikimedia.org/wiki/Special:FilePath/Plat%20%C3%A0%20d%C3%A9cor%20d%27%C3%89cossais%20-%20Expo%20Le%20Monde%20vu%20d%27Asie%20au%20Mus%C3%A9e%20Guimet.jpg?width=400",
      "title": "plat à décor d'Écossais",
      "source": "guimet",
      "tags": [
        "pattern"
      ]
    },
    {
      "img": "https://commons.wikimedia.org/wiki/Special:FilePath/Temple%20in%20rocky%20landscape-AA%20280-IMG%208996.JPG",
      "thumb": "https://commons.wikimedia.org/wiki/Special:FilePath/Temple%20in%20rocky%20landscape-AA%20280-IMG%208996.JPG?width=400",
      "title": "Temple in rocky landscape-AA 280",
      "source": "guimet",
      "tags": [
        "minimal"
      ]
    },
    {
      "img": "https://commons.wikimedia.org/wiki/Special:FilePath/Pancika-AO%202932-IMG%208491-gradient.jpg",
      "thumb": "https://commons.wikimedia.org/wiki/Special:FilePath/Pancika-AO%202932-IMG%208491-gradient.jpg?width=400",
      "title": "Pañcika-AO 2932",
      "source": "guimet",
      "tags": [
        "minimal"
      ]
    },
    {
      "img": "https://commons.wikimedia.org/wiki/Special:FilePath/Vajra%20MA-5212-IMG%208446-gradient.jpg",
      "thumb": "https://commons.wikimedia.org/wiki/Special:FilePath/Vajra%20MA-5212-IMG%208446-gradient.jpg?width=400",
      "title": "vajra-MA 5212",
      "source": "guimet",
      "tags": [
        "minimal"
      ]
    },
    {
      "img": "https://commons.wikimedia.org/wiki/Special:FilePath/Avalokitesvara%20%28mus%C3%A9e%20Guimet%29%20%285422671631%29.jpg",
      "thumb": "https://commons.wikimedia.org/wiki/Special:FilePath/Avalokitesvara%20%28mus%C3%A9e%20Guimet%29%20%285422671631%29.jpg?width=400",
      "title": "bodhisattva Avalokiteshvara on Mount Potalaka-EO 2444",
      "source": "guimet",
      "tags": [
        "urban"
      ]
    },
    {
      "img": "https://commons.wikimedia.org/wiki/Special:FilePath/Standing%20Buddha%20Guimet%20MA2686.jpg",
      "thumb": "https://commons.wikimedia.org/wiki/Special:FilePath/Standing%20Buddha%20Guimet%20MA2686.jpg?width=400",
      "title": "Standing Buddha-MA 2686",
      "source": "guimet",
      "tags": [
        "urban"
      ]
    },
    {
      "img": "https://commons.wikimedia.org/wiki/Special:FilePath/Guimet%20Hebei%20VI.JPG",
      "thumb": "https://commons.wikimedia.org/wiki/Special:FilePath/Guimet%20Hebei%20VI.JPG?width=400",
      "title": "Buddhas Shakyamuni and Prabhutaratna-EO 2604",
      "source": "guimet",
      "tags": [
        "urban"
      ]
    },
    {
      "img": "https://commons.wikimedia.org/wiki/Special:FilePath/Cheval%20terre%20cuites%20a%20gla%C3%A7ure%20trois%20couleurs%20chine%20du%20nord%20VIIs.JPG",
      "thumb": "https://commons.wikimedia.org/wiki/Special:FilePath/Cheval%20terre%20cuites%20a%20gla%C3%A7ure%20trois%20couleurs%20chine%20du%20nord%20VIIs.JPG?width=400",
      "title": "Horse-MA 4805",
      "source": "guimet",
      "tags": [
        "urban"
      ]
    },
    {
      "img": "https://commons.wikimedia.org/wiki/Special:FilePath/Dinastia%20tang%2C%20cavallo%20sellato%2C%20cina%20centrale%2C%20700-750%20ca..JPG",
      "thumb": "https://commons.wikimedia.org/wiki/Special:FilePath/Dinastia%20tang%2C%20cavallo%20sellato%2C%20cina%20centrale%2C%20700-750%20ca..JPG?width=400",
      "title": "Horse-MA 3995",
      "source": "guimet",
      "tags": [
        "urban"
      ]
    },
    {
      "img": "https://commons.wikimedia.org/wiki/Special:FilePath/Dinastia%20han%20anteriore%2C%20cavallo%20stante%2C%20cina%20del%20nord%2C%20II-I%20sec.%20ac..JPG",
      "thumb": "https://commons.wikimedia.org/wiki/Special:FilePath/Dinastia%20han%20anteriore%2C%20cavallo%20stante%2C%20cina%20del%20nord%2C%20II-I%20sec.%20ac..JPG?width=400",
      "title": "Horse-MA 6090",
      "source": "guimet",
      "tags": [
        "urban"
      ]
    },
    {
      "img": "https://commons.wikimedia.org/wiki/Special:FilePath/Dinastia%20tang%2C%20cavallo%20sellato%2C%20cina%20del%20nord%2C%20VIII%20sec.JPG",
      "thumb": "https://commons.wikimedia.org/wiki/Special:FilePath/Dinastia%20tang%2C%20cavallo%20sellato%2C%20cina%20del%20nord%2C%20VIII%20sec.JPG?width=400",
      "title": "Horse-MA 6111",
      "source": "guimet",
      "tags": [
        "urban"
      ]
    },
    {
      "img": "https://commons.wikimedia.org/wiki/Special:FilePath/Dinastia%20wei%2C%20cavallo%20sellato%2C%20cina%20del%20nord%2C%20vi%20sec.JPG",
      "thumb": "https://commons.wikimedia.org/wiki/Special:FilePath/Dinastia%20wei%2C%20cavallo%20sellato%2C%20cina%20del%20nord%2C%20vi%20sec.JPG?width=400",
      "title": "Horse-MA 4074",
      "source": "guimet",
      "tags": [
        "urban"
      ]
    },
    {
      "img": "https://commons.wikimedia.org/wiki/Special:FilePath/Guimet%20cheval%20epoque%20kofun%20Vs.JPG",
      "thumb": "https://commons.wikimedia.org/wiki/Special:FilePath/Guimet%20cheval%20epoque%20kofun%20Vs.JPG?width=400",
      "title": "Horse-MA 1641",
      "source": "guimet",
      "tags": [
        "urban"
      ]
    },
    {
      "img": "https://commons.wikimedia.org/wiki/Special:FilePath/Dinastia%20han%20anteriore%2C%20cavaliere%2C%20cina%20del%20nord%2C%20II%20sec.%20ac..JPG",
      "thumb": "https://commons.wikimedia.org/wiki/Special:FilePath/Dinastia%20han%20anteriore%2C%20cavaliere%2C%20cina%20del%20nord%2C%20II%20sec.%20ac..JPG?width=400",
      "title": "Horse-MA 6069",
      "source": "guimet",
      "tags": [
        "urban"
      ]
    },
    {
      "img": "https://commons.wikimedia.org/wiki/Special:FilePath/Ornated%20architecture%20element-MG%2023715-IMG%208623-gradient.jpg",
      "thumb": "https://commons.wikimedia.org/wiki/Special:FilePath/Ornated%20architecture%20element-MG%2023715-IMG%208623-gradient.jpg?width=400",
      "title": "Ornated architecture element-MG 23715",
      "source": "guimet",
      "tags": [
        "urban"
      ]
    },
    {
      "img": "https://commons.wikimedia.org/wiki/Special:FilePath/Ornated%20architecture%20element-MG%2023575-IMG%208620-gradient.jpg",
      "thumb": "https://commons.wikimedia.org/wiki/Special:FilePath/Ornated%20architecture%20element-MG%2023575-IMG%208620-gradient.jpg?width=400",
      "title": "Ornated architecture element-MG 23575",
      "source": "guimet",
      "tags": [
        "urban"
      ]
    },
    {
      "img": "https://commons.wikimedia.org/wiki/Special:FilePath/Mus%C3%A9e%20Guimet%20-%20Le%20Monde%20vu%20d%27Asie%20-%20Cosmogramme%20avec%20le%20Mont%20Meru%20-%20gradient.jpg",
      "thumb": "https://commons.wikimedia.org/wiki/Special:FilePath/Mus%C3%A9e%20Guimet%20-%20Le%20Monde%20vu%20d%27Asie%20-%20Cosmogramme%20avec%20le%20Mont%20Meru%20-%20gradient.jpg?width=400",
      "title": "Cosmogram with Mount Meru - EG 632",
      "source": "guimet",
      "tags": [
        "urban"
      ]
    },
    {
      "img": "https://commons.wikimedia.org/wiki/Special:FilePath/Atlas%20Ch%E2%80%99onhado%20-%20Expo%20Le%20Monde%20vu%20d%27Asie%20au%20Mus%C3%A9e%20Guimet.jpg",
      "thumb": "https://commons.wikimedia.org/wiki/Special:FilePath/Atlas%20Ch%E2%80%99onhado%20-%20Expo%20Le%20Monde%20vu%20d%27Asie%20au%20Mus%C3%A9e%20Guimet.jpg?width=400",
      "title": "Atlas Ch'onhado",
      "source": "guimet",
      "tags": [
        "urban"
      ]
    },
    {
      "img": "https://commons.wikimedia.org/wiki/Special:FilePath/Boussole%20g%C3%A9omantique%20-%20Expo%20Le%20Monde%20vu%20d%27Asie%20au%20Mus%C3%A9e%20Guimet.jpg",
      "thumb": "https://commons.wikimedia.org/wiki/Special:FilePath/Boussole%20g%C3%A9omantique%20-%20Expo%20Le%20Monde%20vu%20d%27Asie%20au%20Mus%C3%A9e%20Guimet.jpg?width=400",
      "title": "Boussole géomantique",
      "source": "guimet",
      "tags": [
        "urban"
      ]
    }
  ]
}